Workbook

Sheet Résumé de l’exportation
B3: Ce document a été exporté depuis Numbers. Chaque tableau a été converti en feuille de calcul Excel. Tous les autres objets sur chaque feuille Numbers ont été placés sur des feuilles de calcul différentes. Veuillez noter que les calculs de formules peuvent être différents dans Excel.
B7: Nom de la feuille Numbers | C7: Nom du tableau Numbers | D7: Nom de la feuille de calcul Excel
B9: SAMPLE - Monthly Profit & Loss
C10: Table 1 | D10: SAMPLE - Monthly Profit & Loss
B11: SAMPLE - Monthly Profit & Loss-1
C12: Table 1 | D12: SAMPLE - Monthly Profit & Loss-
B13: SAMPLE - Profit & Loss YTD
C14: Table 1 | D14: SAMPLE - Profit & Loss YTD - Ta
B15: BLANK - Monthly Profit & Loss
C16: Table 1 | D16: BLANK - Monthly Profit & Loss -
B17: BLANK - Profit & Loss YTD
C18: Table 1 | D18: BLANK - Profit & Loss YTD - Tab

Sheet SAMPLE - Monthly Profit & Loss 
B1: MONTHLY PROFIT AND LOSS
B2: COMPANY NAME
B3: Hackboot
B5: Last Update and verification
B6: 45984
C8: TREND | D8: JANUARY | E8: FEBRUARY | F8: MARCH | G8: APRIL | H8: MAY | I8: JUNE | J8: JULY | K8: AUGUST | L8: SEPTEMBER | M8: OCTOBER | N8: NOVEMBER | O8: DECEMBER | Q8: YTD
B9: GROSS PROFIT | D9: {=D39} -> 18640.8 | E9: {=E39} -> 12440.4 | F9: {=F39} -> 22052.4 | G9: {=G39} -> 26091.6 | H9: {=H39} -> 12633.2 | I9: {=I39} -> 25394.4 | J9: {=J39} -> 0 | K9: {=K39} -> 0 | ... O9: {=O39} -> 7408.68 | Q9: {=SUM(D9:O9)} -> 131824.98
B10: TOTAL EXPENSES | D10: {=D113} -> 13441.7 | E10: {=E113} -> 9888.9 | F10: {=F113} -> 16814.8 | G10: {=G113} -> 18128.1 | H10: {=H113} -> 13110 | I10: {=I113} -> 20072.6 | J10: {=J113} -> 0 | K10: {=K113} -> 0 | ... O10: {=O113} -> 0 | Q10: {=SUM(D10:O10)} -> 91456.1
B11: PROFIT / LOSS | D11: {=D9-D10} -> 5199.1 | E11: {=E9-E10} -> 2551.5 | F11: {=F9-F10} -> 5237.6 | G11: {=G9-G10} -> 7963.5 | H11: {=H9-H10} -> -476.8 | I11: {=I9-I10} -> 5321.8 | J11: {=J9-J10} -> 0 | K11: {=K9-K10} -> 0 | ... O11: {=O9-O10} -> 7408.68 | Q11: {=Q9-Q10} -> 40368.88
B13: Clients
C14: TREND | D14: JANUARY | E14: FEBRUARY | F14: MARCH | G14: APRIL | H14: MAY | I14: JUNE | J14: JULY | K14: AUGUST | L14: SEPTEMBER | M14: OCTOBER | N14: NOVEMBER | O14: DECEMBER | Q14: YTD
B15: Pack Essentiel | D15: 0 | E15: 0 | F15: 0 | G15: 0 | H15: 0 | I15: 0 | J15: 0 | K15: 0 | L15: 12 | M15: 49 | N15: 89 | O15: 132 | Q15: {=SUM(D15:O15)} -> 282
B16: Pack Avantage | D16: 0 | E16: 0 | F16: 0 | G16: 0 | H16: 0 | I16: 0 | J16: 0 | K16: 0 | L16: 4 | M16: 16 | N16: 51 | O16: 78 | Q16: {=SUM(D16:O16)} -> 149
B17: Pack Élite | D17: 0 | E17: 0 | F17: 0 | G17: 0 | H17: 0 | I17: 0 | J17: 0 | K17: 0 | L17: 0 | M17: 7 | N17: 21 | O17: 34 | Q17: {=SUM(D17:O17)} -> 62
B18: VM Clash Royal | D18: 23 | E18: 31 | F18: 12 | G18: 7 | H18: 4 | I18: 26 | J18: 0 | K18: 0 | L18: 0 | M18: 0 | N18: 0 | O18: 0 | Q18: {=SUM(D18:O18)} -> 103
B19: VM Call Of Duty | D19: 8 | E19: 4 | F19: 9 | G19: 13 | H19: 3 | I19: 7 | J19: 0 | K19: 0 | L19: 0 | M19: 0 | N19: 0 | O19: 0 | Q19: {=SUM(D19:O19)} -> 44
B20: VM Overwatch 2 | D20: 2 | E20: 1 | F20: 6 | G20: 4 | H20: 8 | I20: 11 | J20: 0 | K20: 0 | L20: 0 | M20: 0 | N20: 0 | O20: 0 | Q20: {=SUM(D20:O20)} -> 32
B21: TOTAUX | D21: {=SUM(D15,D17,D18,D16,D19,D20)} -> 33 | E21: {=SUM(E15,E17,E18,E16,E19,E20)} -> 36 | F21: {=SUM(F15,F17,F18,F16,F19,F20)} -> 27 | G21: {=SUM(G15,G17,G18,G16,G19,G20)} -> 24 | H21: {=SUM(H15,H17,H18,H16,H19,H20)} -> 15 | I21: {=SUM(I15,I17,I18,I16,I19,I20)} -> 44 | J21: {=SUM(J15,J17,J18,J16,J19,J20)} -> 0 | K21: {=SUM(K15,K17,K18,K16,K19,K20)} -> 0 | ... O21: {=SUM(O15,O17,O18,O16,O19,O20)} -> 244 | Q21: {=SUM(Q15,Q16,Q17,Q18,Q19,Q20)} -> 672
B23: Enter the amounts for each month below. YTD amounts, YTD tab, graph, and trend lines will populate automatically.
B24: REVENUE | C24: TREND | D24: JANUARY | E24: FEBRUARY | F24: MARCH | G24: APRIL | H24: MAY | I24: JUNE | J24: JULY | K24: AUGUST | L24: SEPTEMBER | M24: OCTOBER | N24: NOVEMBER | O24: DECEMBER | Q24: YTD
B25: Pack Essentiel | D25: {=SUM(19.99*D15)} -> 0 | E25: {=SUM(19.99*E15)} -> 0 | F25: {=SUM(19.99*F15)} -> 0 | G25: {=SUM(19.99*G15)} -> 0 | H25: {=SUM(19.99*H15)} -> 0 | I25: {=SUM(19.99*I15)} -> 0 | J25: {=SUM(19.99*J15)} -> 0 | K25: {=SUM(19.99*K15)} -> 0 | ... O25: {=SUM(19.99*O15)} -> 2638.68 | Q25: {=SUM(D25:O25)} -> 5637.18
B26: Pack Avantage | D26: {=SUM(35*D16)} -> 0 | E26: {=SUM(35*E16)} -> 0 | F26: {=SUM(35*F16)} -> 0 | G26: {=SUM(35*G16)} -> 0 | H26: {=SUM(35*H16)} -> 0 | I26: {=SUM(35*I16)} -> 0 | J26: {=SUM(35*J16)} -> 0 | K26: {=SUM(35*K16)} -> 0 | ... O26: {=SUM(35*O16)} -> 2730 | Q26: {=SUM(D26:O26)} -> 5215
B27: Pack Élite | D27: {=SUM(60*D17)} -> 0 | E27: {=SUM(60*E17)} -> 0 | F27: {=SUM(60*F17)} -> 0 | G27: {=SUM(60*G17)} -> 0 | H27: {=SUM(60*H17)} -> 0 | I27: {=SUM(60*I17)} -> 0 | J27: {=SUM(60*J17)} -> 0 | K27: {=SUM(60*K17)} -> 0 | ... O27: {=SUM(60*O17)} -> 2040 | Q27: {=SUM(D27:O27)} -> 3720
B28: VM Clash Royal | D28: {=SUM(160*D18)} -> 3680 | E28: {=SUM(160*E18)} -> 4960 | F28: {=SUM(160*F18)} -> 1920 | G28: {=SUM(160*G18)} -> 1120 | H28: {=SUM(160*H18)} -> 640 | I28: {=SUM(160*I18)} -> 4160 | J28: {=SUM(160*J18)} -> 0 | K28: {=SUM(160*K18)} -> 0 | ... O28: {=SUM(160*O18)} -> 0 | Q28: {=SUM(D28:O28)} -> 16480
B29: VM Call Of Duty | D29: {=SUM(1650*D19)} -> 13200 | E29: {=SUM(1650*E19)} -> 6600 | F29: {=SUM(1650*F19)} -> 14850 | G29: {=SUM(1650*G19)} -> 21450 | H29: {=SUM(1650*H19)} -> 4950 | I29: {=SUM(1650*I19)} -> 11550 | J29: {=SUM(1650*J19)} -> 0 | K29: {=SUM(1650*K19)} -> 0 | ... O29: {=SUM(1650*O19)} -> 0 | Q29: {=SUM(D29:O29)} -> 72600
B30: VM Overwatch 2 | D30: {=SUM(880.4*D20)} -> 1760.8 | E30: {=SUM(880.4*E20)} -> 880.4 | F30: {=SUM(880.4*F20)} -> 5282.4 | G30: {=SUM(880.4*G20)} -> 3521.6 | H30: {=SUM(880.4*H20)} -> 7043.2 | I30: {=SUM(880.4*I20)} -> 9684.4 | J30: {=SUM(880.4*J20)} -> 0 | K30: {=SUM(880.4*K20)} -> 0 | ... O30: {=SUM(880.4*O20)} -> 0 | Q30: {=SUM(D30:O30)} -> 28172.8
B31: TOTAL REVENUE | D31: {=SUM(D25:D30)} -> 18640.8 | E31: {=SUM(E25:E30)} -> 12440.4 | F31: {=SUM(F25:F30)} -> 22052.4 | G31: {=SUM(G25:G30)} -> 26091.6 | H31: {=SUM(H25:H30)} -> 12633.2 | I31: {=SUM(I25:I30)} -> 25394.4 | J31: {=SUM(J25:J30)} -> 0 | K31: {=SUM(K25:K30)} -> 0 | ... O31: {=SUM(O25:O30)} -> 7408.68 | Q31: {=SUM(Q25:Q30)} -> 131824.98
B33: REDUCTIONS | C33: TREND | D33: JANUARY | E33: FEBRUARY | F33: MARCH | G33: APRIL | H33: MAY | I33: JUNE | J33: JULY | K33: AUGUST | L33: SEPTEMBER | M33: OCTOBER | N33: NOVEMBER | O33: DECEMBER | Q33: YTD
B34: Less Sales Returns | D34: 0 | E34: 0 | F34: 0 | G34: 0 | H34: 0 | I34: 0 | J34: 0 | K34: 0 | L34: 0 | M34: 0 | N34: 0 | O34: 0 | Q34: {=SUM(D34:O34)} -> 0
B35: Less Sales Discounts | D35: 0 | E35: 0 | F35: 0 | G35: 0 | H35: 0 | I35: 0 | J35: 0 | K35: 0 | L35: 0 | M35: 0 | N35: 0 | O35: 0 | Q35: {=SUM(D35:O35)} -> 0
B36: Less Cost of Goods Sold | D36: 0 | E36: 0 | F36: 0 | G36: 0 | H36: 0 | I36: 0 | J36: 0 | K36: 0 | L36: 0 | M36: 0 | N36: 0 | O36: 0 | Q36: {=SUM(D36:O36)} -> 0
B37: TOTAL REDUCTIONS | D37: {=SUM(D34:D36)} -> 0 | E37: {=SUM(E34:E36)} -> 0 | F37: {=SUM(F34:F36)} -> 0 | G37: {=SUM(G34:G36)} -> 0 | H37: {=SUM(H34:H36)} -> 0 | I37: {=SUM(I34:I36)} -> 0 | J37: {=SUM(J34:J36)} -> 0 | K37: {=SUM(K34:K36)} -> 0 | ... O37: {=SUM(O34:O36)} -> 0 | Q37: {=SUM(Q34:Q36)} -> 0
B39: GROSS PROFIT | SALES MINUS REDUCTIONS | D39: {=D31-D37} -> 18640.8 | E39: {=E31-E37} -> 12440.4 | F39: {=F31-F37} -> 22052.4 | G39: {=G31-G37} -> 26091.6 | H39: {=H31-H37} -> 12633.2 | I39: {=I31-I37} -> 25394.4 | J39: {=J31-J37} -> 0 | K39: {=K31-K37} -> 0 | ... O39: {=O31-O37} -> 7408.68 | Q39: {=Q31-Q37} -> 131824.98
B41: EXPENSES
B42: EMPLOYEE | C42: TREND | D42: JANUARY | E42: FEBRUARY | F42: MARCH | G42: APRIL | H42: MAY | I42: JUNE | J42: JULY | K42: AUGUST | L42: SEPTEMBER | M42: OCTOBER | N42: NOVEMBER | O42: DECEMBER | Q42: YTD
B43: Luf | C43: Freelance | D43: 4000 | E43: 4000 | F43: 4000 | G43: 4000 | H43: 4000 | I43: 4000 | J43: 0 | K43: 0 | L43: 0 | M43: 0 | N43: 0 | O43: 0 | Q43: {=SUM(D43:O43)} -> 24000
B44: Gengis | D44: 0 | E44: 0 | F44: 0 | G44: 0 | H44: 0 | I44: 0 | J44: 0 | K44: 0 | L44: 0 | M44: 0 | N44: 0 | O44: 0 | Q44: {=SUM(D44:O44)} -> 0
B45: Other | D45: 0 | E45: 0 | F45: 0 | G45: 0 | H45: 0 | I45: 0 | J45: 0 | K45: 0 | L45: 0 | M45: 0 | N45: 0 | O45: 0 | Q45: {=SUM(D45:O45)} -> 0
B46: Other | D46: 0 | E46: 0 | F46: 0 | G46: 0 | H46: 0 | I46: 0 | J46: 0 | K46: 0 | L46: 0 | M46: 0 | N46: 0 | O46: 0 | Q46: {=SUM(D46:O46)} -> 0
B47: Other | D47: 0 | E47: 0 | F47: 0 | G47: 0 | H47: 0 | I47: 0 | J47: 0 | K47: 0 | L47: 0 | M47: 0 | N47: 0 | O47: 0 | Q47: {=SUM(D47:O47)} -> 0
B48: Other | D48: 0 | E48: 0 | F48: 0 | G48: 0 | H48: 0 | I48: 0 | J48: 0 | K48: 0 | L48: 0 | M48: 0 | N48: 0 | O48: 0 | Q48: {=SUM(D48:O48)} -> 0
B49: Other | D49: 0 | E49: 0 | F49: 0 | G49: 0 | H49: 0 | I49: 0 | J49: 0 | K49: 0 | L49: 0 | M49: 0 | N49: 0 | O49: 0 | Q49: {=SUM(D49:O49)} -> 0
B50: Other | D50: 0 | E50: 0 | F50: 0 | G50: 0 | H50: 0 | I50: 0 | J50: 0 | K50: 0 | L50: 0 | M50: 0 | N50: 0 | O50: 0 | Q50: {=SUM(D50:O50)} -> 0
B51: Other | D51: 0 | E51: 0 | F51: 0 | G51: 0 | H51: 0 | I51: 0 | J51: 0 | K51: 0 | L51: 0 | M51: 0 | N51: 0 | O51: 0 | Q51: {=SUM(D51:O51)} -> 0
B52: Other | D52: 0 | E52: 0 | F52: 0 | G52: 0 | H52: 0 | I52: 0 | J52: 0 | K52: 0 | L52: 0 | M52: 0 | N52: 0 | O52: 0 | Q52: {=SUM(D52:O52)} -> 0
B53: Other | D53: 0 | E53: 0 | F53: 0 | G53: 0 | H53: 0 | I53: 0 | J53: 0 | K53: 0 | L53: 0 | M53: 0 | N53: 0 | O53: 0 | Q53: {=SUM(D53:O53)} -> 0
B54: Other | D54: 0 | E54: 0 | F54: 0 | G54: 0 | H54: 0 | I54: 0 | J54: 0 | K54: 0 | L54: 0 | M54: 0 | N54: 0 | O54: 0 | Q54: {=SUM(D54:O54)} -> 0
B55: Other | D55: 0 | E55: 0 | F55: 0 | G55: 0 | H55: 0 | I55: 0 | J55: 0 | K55: 0 | L55: 0 | M55: 0 | N55: 0 | O55: 0 | Q55: {=SUM(D55:O55)} -> 0
... B57: Other | D57: 0 | E57: 0 | F57: 0 | G57: 0 | H57: 0 | I57: 0 | J57: 0 | K57: 0 | L57: 0 | M57: 0 | N57: 0 | O57: 0 | Q57: {=SUM(D57:O57)} -> 0
B58: TOTAL EMPLOYEE AND LABOR EXPENSE | D58: {=SUM(D43:D57)} -> 4000 | E58: {=SUM(E43:E57)} -> 4000 | F58: {=SUM(F43:F57)} -> 4000 | G58: {=SUM(G43:G57)} -> 4000 | H58: {=SUM(H43:H57)} -> 4000 | I58: {=SUM(I43:I57)} -> 4000 | J58: {=SUM(J43:J57)} -> 0 | K58: {=SUM(K43:K57)} -> 0 | ... O58: {=SUM(O43:O57)} -> 0 | Q58: {=SUM(Q43:Q57)} -> 24000
B60: Software | C60: TREND | D60: JANUARY | E60: FEBRUARY | F60: MARCH | G60: APRIL | H60: MAY | I60: JUNE | J60: JULY | K60: AUGUST | L60: SEPTEMBER | M60: OCTOBER | N60: NOVEMBER | O60: DECEMBER | Q60: YTD
B61: AWS - Clash Royal | C61: t3.large | D61: {=SUM(59.9*D18)} -> 1377.7 | E61: {=SUM(59.9*E18)} -> 1856.9 | F61: {=SUM(59.9*F18)} -> 718.8 | G61: {=SUM(59.9*G18)} -> 419.3 | H61: {=SUM(59.9*H18)} -> 239.6 | I61: {=SUM(59.9*I18)} -> 1557.4 | J61: {=SUM(59.9*J18)} -> 0 | K61: {=SUM(59.9*K18)} -> 0 | ... O61: {=SUM(59.9*O18)} -> 0 | Q61: {=SUM(D61:O61)} -> 6169.7
B62: AWS - Overwatch 2 | C62: g4dn.2xlarge | D62: {=SUM(806.4*D20)} -> 1612.8 | E62: {=SUM(806.4*E20)} -> 806.4 | F62: {=SUM(806.4*F20)} -> 4838.4 | G62: {=SUM(806.4*G20)} -> 3225.6 | H62: {=SUM(806.4*H20)} -> 6451.2 | I62: {=SUM(806.4*I20)} -> 8870.4 | J62: {=SUM(806.4*J20)} -> 0 | K62: {=SUM(806.4*K20)} -> 0 | ... O62: {=SUM(806.4*O20)} -> 0 | Q62: {=SUM(D62:O62)} -> 25804.8
B63: AWS - Call Of Duty | C63: g4dn.2xlarge | D63: {=SUM(806.4*D19)} -> 6451.2 | E63: {=SUM(806.4*E19)} -> 3225.6 | F63: {=SUM(806.4*F19)} -> 7257.6 | G63: {=SUM(806.4*G19)} -> 10483.2 | H63: {=SUM(806.4*H19)} -> 2419.2 | I63: {=SUM(806.4*I19)} -> 5644.8 | J63: {=SUM(806.4*J19)} -> 0 | K63: {=SUM(806.4*K19)} -> 0 | ... O63: {=SUM(806.4*O19)} -> 0 | Q63: {=SUM(D63:O63)} -> 35481.6
B64: LMS | C64: sub constant | D64: 0 | E64: 0 | F64: 0 | G64: 0 | H64: 0 | I64: 0 | J64: 0 | K64: 0 | L64: 0 | M64: 0 | N64: 0 | O64: 0 | Q64: {=SUM(D64:O64)} -> 0
B65: Other | D65: 0 | E65: 0 | F65: 0 | G65: 0 | H65: 0 | I65: 0 | J65: 0 | K65: 0 | L65: 0 | M65: 0 | N65: 0 | O65: 0 | Q65: {=SUM(D65:O65)} -> 0
D66: {=SUM(D61:D65)} -> 9441.7 | E66: {=SUM(E61:E65)} -> 5888.9 | F66: {=SUM(F61:F65)} -> 12814.8 | G66: {=SUM(G61:G65)} -> 14128.1 | H66: {=SUM(H61:H65)} -> 9110 | I66: {=SUM(I61:I65)} -> 16072.6 | J66: {=SUM(J61:J65)} -> 0 | K66: {=SUM(K61:K65)} -> 0 | ... O66: {=SUM(O61:O65)} -> 0 | Q66: {=SUM(Q61:Q65)} -> 67456.1
B68: BANKING AND FINANCE | C68: TREND | D68: JANUARY | E68: FEBRUARY | F68: MARCH | G68: APRIL | H68: MAY | I68: JUNE | J68: JULY | K68: AUGUST | L68: SEPTEMBER | M68: OCTOBER | N68: NOVEMBER | O68: DECEMBER | Q68: YTD
B69: Bank Fees | D69: 0 | E69: 0 | F69: 0 | G69: 0 | H69: 0 | I69: 0 | J69: 0 | K69: 0 | L69: 0 | M69: 0 | N69: 0 | O69: 0 | Q69: {=SUM(D69:O69)} -> 0
B70: Bad Debts | D70: 0 | E70: 0 | F70: 0 | G70: 0 | H70: 0 | I70: 0 | J70: 0 | K70: 0 | L70: 0 | M70: 0 | N70: 0 | O70: 0 | Q70: {=SUM(D70:O70)} -> 0
B71: Interest Paid | D71: 0 | E71: 0 | F71: 0 | G71: 0 | H71: 0 | I71: 0 | J71: 0 | K71: 0 | L71: 0 | M71: 0 | N71: 0 | O71: 0 | Q71: {=SUM(D71:O71)} -> 0
B72: Insurance | D72: 0 | E72: 0 | F72: 0 | G72: 0 | H72: 0 | I72: 0 | J72: 0 | K72: 0 | L72: 0 | M72: 0 | N72: 0 | O72: 0 | Q72: {=SUM(D72:O72)} -> 0
B73: Loan Fees | D73: 0 | E73: 0 | F73: 0 | G73: 0 | H73: 0 | I73: 0 | J73: 0 | K73: 0 | L73: 0 | M73: 0 | N73: 0 | O73: 0 | Q73: {=SUM(D73:O73)} -> 0
B74: Other | D74: 0 | E74: 0 | F74: 0 | G74: 0 | H74: 0 | I74: 0 | J74: 0 | K74: 0 | L74: 0 | M74: 0 | N74: 0 | O74: 0 | Q74: {=SUM(D74:O74)} -> 0
B75: TOTAL BANKING AND FINANCE | D75: {=SUM(D69:D74)} -> 0 | E75: {=SUM(E69:E74)} -> 0 | F75: {=SUM(F69:F74)} -> 0 | G75: {=SUM(G69:G74)} -> 0 | H75: {=SUM(H69:H74)} -> 0 | I75: {=SUM(I69:I74)} -> 0 | J75: {=SUM(J69:J74)} -> 0 | K75: {=SUM(K69:K74)} -> 0 | ... O75: {=SUM(O69:O74)} -> 0 | Q75: {=SUM(Q69:Q74)} -> 0
B77: GENERAL BUSINESS | C77: TREND | D77: JANUARY | E77: FEBRUARY | F77: MARCH | G77: APRIL | H77: MAY | I77: JUNE | J77: JULY | K77: AUGUST | L77: SEPTEMBER | M77: OCTOBER | N77: NOVEMBER | O77: DECEMBER | Q77: YTD
B78: AWS - | C78: 20/user | D78: 0 | E78: 0 | F78: 0 | G78: 0 | H78: 0 | I78: 0 | J78: 0 | K78: 0 | L78: 0 | M78: 0 | N78: 0 | O78: 0 | Q78: {=SUM(D78:O78)} -> 0
B79: Maintenance and Repairs - OVH Cloud | C79: sub constant | D79: 0 | E79: 0 | F79: 0 | G79: 0 | H79: 0 | I79: 0 | J79: 0 | K79: 0 | L79: 0 | M79: 0 | N79: 0 | O79: 0 | Q79: {=SUM(D79:O79)} -> 0
B80: Telecommunication | C80: 90/user | D80: 0 | E80: 0 | F80: 0 | G80: 0 | H80: 0 | I80: 0 | J80: 0 | K80: 0 | L80: 0 | M80: 0 | N80: 0 | O80: 0 | Q80: {=SUM(D80:O80)} -> 0
B81: Advertising, Marketing, and Promotions | C81: sub constant | D81: 0 | E81: 0 | F81: 0 | G81: 0 | H81: 0 | I81: 0 | J81: 0 | K81: 0 | L81: 0 | M81: 0 | N81: 0 | O81: 0 | Q81: {=SUM(D81:O81)} -> 0
B82: Web Hosting | C82: sub constant | D82: 0 | E82: 0 | F82: 0 | G82: 0 | H82: 0 | I82: 0 | J82: 0 | K82: 0 | L82: 0 | M82: 0 | N82: 0 | O82: 0 | Q82: {=SUM(D82:O82)} -> 0
B83: LMS Manager | C83: sub constant | D83: 0 | E83: 0 | F83: 0 | G83: 0 | H83: 0 | I83: 0 | J83: 0 | K83: 0 | L83: 0 | M83: 0 | N83: 0 | O83: 0 | Q83: {=SUM(D83:O83)} -> 0
B84: Office Supplies | D84: 0 | E84: 0 | F84: 0 | G84: 0 | H84: 0 | I84: 0 | J84: 0 | K84: 0 | L84: 0 | M84: 0 | N84: 0 | O84: 0 | Q84: {=SUM(D84:O84)} -> 0
B85: Professional Dues | D85: 0 | E85: 0 | F85: 0 | G85: 0 | H85: 0 | I85: 0 | J85: 0 | K85: 0 | L85: 0 | M85: 0 | N85: 0 | O85: 0 | Q85: {=SUM(D85:O85)} -> 0
B86: Subscriptions | D86: 0 | E86: 0 | F86: 0 | G86: 0 | H86: 0 | I86: 0 | J86: 0 | K86: 0 | L86: 0 | M86: 0 | N86: 0 | O86: 0 | Q86: {=SUM(D86:O86)} -> 0
B87: Freight | D87: 0 | E87: 0 | F87: 0 | G87: 0 | H87: 0 | I87: 0 | J87: 0 | K87: 0 | L87: 0 | M87: 0 | N87: 0 | O87: 0 | Q87: {=SUM(D87:O87)} -> 0
B88: Postage and Shipping | D88: 0 | E88: 0 | F88: 0 | G88: 0 | H88: 0 | I88: 0 | J88: 0 | K88: 0 | L88: 0 | M88: 0 | N88: 0 | O88: 0 | Q88: {=SUM(D88:O88)} -> 0
B89: Depreciation and Amortization | D89: 0 | E89: 0 | F89: 0 | G89: 0 | H89: 0 | I89: 0 | J89: 0 | K89: 0 | L89: 0 | M89: 0 | N89: 0 | O89: 0 | Q89: {=SUM(D89:O89)} -> 0
B90: Travel | D90: 0 | E90: 0 | F90: 0 | G90: 0 | H90: 0 | I90: 0 | J90: 0 | K90: 0 | L90: 0 | M90: 0 | N90: 0 | O90: 0 | Q90: {=SUM(D90:O90)} -> 0
B91: Technical Licenses | D91: 0 | E91: 0 | F91: 0 | G91: 0 | H91: 0 | I91: 0 | J91: 0 | K91: 0 | L91: 0 | M91: 0 | N91: 0 | O91: 0 | Q91: {=SUM(D91:O91)} -> 0
B92: Meals and Entertainment | D92: 0 | E92: 0 | F92: 0 | G92: 0 | H92: 0 | I92: 0 | J92: 0 | K92: 0 | L92: 0 | M92: 0 | N92: 0 | O92: 0 | Q92: {=SUM(D92:O92)} -> 0
B93: Patent Fees | D93: 0 | E93: 0 | F93: 0 | G93: 0 | H93: 0 | I93: 0 | J93: 0 | K93: 0 | L93: 0 | M93: 0 | N93: 0 | O93: 0 | Q93: {=SUM(D93:O93)} -> 0
B94: Losses from Legal Actions | D94: 0 | E94: 0 | F94: 0 | G94: 0 | H94: 0 | I94: 0 | J94: 0 | K94: 0 | L94: 0 | M94: 0 | N94: 0 | O94: 0 | Q94: {=SUM(D94:O94)} -> 0
B95: Other | D95: 0 | E95: 0 | F95: 0 | G95: 0 | H95: 0 | I95: 0 | J95: 0 | K95: 0 | L95: 0 | M95: 0 | N95: 0 | O95: 0 | Q95: {=SUM(D95:O95)} -> 0
B96: TOTAL GENERAL BUSINESS | D96: {=SUM(D78:D95)} -> 0 | E96: {=SUM(E78:E95)} -> 0 | F96: {=SUM(F78:F95)} -> 0 | G96: {=SUM(G78:G95)} -> 0 | H96: {=SUM(H78:H95)} -> 0 | I96: {=SUM(I78:I95)} -> 0 | J96: {=SUM(J78:J95)} -> 0 | K96: {=SUM(K78:K95)} -> 0 | ... O96: {=SUM(O78:O95)} -> 0 | Q96: {=SUM(Q78:Q95)} -> 0
B98: VEHICLE EXPENSE | C98: TREND | D98: JANUARY | E98: FEBRUARY | F98: MARCH | G98: APRIL | H98: MAY | I98: JUNE | J98: JULY | K98: AUGUST | L98: SEPTEMBER | M98: OCTOBER | N98: NOVEMBER | O98: DECEMBER | Q98: YTD
B99: Gas | D99: 0 | E99: 0 | F99: 0 | G99: 0 | H99: 0 | I99: 0 | J99: 0 | K99: 0 | L99: 0 | M99: 0 | N99: 0 | O99: 0 | Q99: {=SUM(D99:O99)} -> 0
B100: Maintenance and Repairs | D100: 0 | E100: 0 | F100: 0 | G100: 0 | H100: 0 | I100: 0 | J100: 0 | K100: 0 | L100: 0 | M100: 0 | N100: 0 | O100: 0 | Q100: {=SUM(D100:O100)} -> 0
B101: Licensing | D101: 0 | E101: 0 | F101: 0 | G101: 0 | H101: 0 | I101: 0 | J101: 0 | K101: 0 | L101: 0 | M101: 0 | N101: 0 | O101: 0 | Q101: {=SUM(D101:O101)} -> 0
B102: Insurance | D102: 0 | E102: 0 | F102: 0 | G102: 0 | H102: 0 | I102: 0 | J102: 0 | K102: 0 | L102: 0 | M102: 0 | N102: 0 | O102: 0 | Q102: {=SUM(D102:O102)} -> 0
B103: Other | D103: 0 | E103: 0 | F103: 0 | G103: 0 | H103: 0 | I103: 0 | J103: 0 | K103: 0 | L103: 0 | M103: 0 | N103: 0 | O103: 0 | Q103: {=SUM(D103:O103)} -> 0
B104: TOTAL VEHICLE EXPENSE | D104: {=SUM(D99:D103)} -> 0 | E104: {=SUM(E99:E103)} -> 0 | F104: {=SUM(F99:F103)} -> 0 | G104: {=SUM(G99:G103)} -> 0 | H104: {=SUM(H99:H103)} -> 0 | I104: {=SUM(I99:I103)} -> 0 | J104: {=SUM(J99:J103)} -> 0 | K104: {=SUM(K99:K103)} -> 0 | ... O104: {=SUM(O99:O103)} -> 0 | Q104: {=SUM(Q99:Q103)} -> 0
B106: TAXES (not calculated) | C106: TREND | D106: JANUARY | E106: FEBRUARY | F106: MARCH | G106: APRIL | H106: MAY | I106: JUNE | J106: JULY | K106: AUGUST | L106: SEPTEMBER | M106: OCTOBER | N106: NOVEMBER | O106: DECEMBER | Q106: YTD
B107: TVA | D107: 0 | E107: 0 | F107: 0 | G107: 0 | H107: 0 | I107: 0 | J107: 0 | K107: 0 | L107: 0 | M107: 0 | N107: 0 | O107: 0 | Q107: {=SUM(D107:O107)} -> 0
B108: Disbursement fees | D108: 0 | E108: 0 | F108: 0 | G108: 0 | H108: 0 | I108: 0 | J108: 0 | K108: 0 | L108: 0 | M108: 0 | N108: 0 | O108: 0 | Q108: {=SUM(D108:O108)} -> 0
B109: Property Tax | D109: 0 | E109: 0 | F109: 0 | G109: 0 | H109: 0 | I109: 0 | J109: 0 | K109: 0 | L109: 0 | M109: 0 | N109: 0 | O109: 0 | Q109: {=SUM(D109:O109)} -> 0
B110: B&O Tax | D110: 0 | E110: 0 | F110: 0 | G110: 0 | H110: 0 | I110: 0 | J110: 0 | K110: 0 | L110: 0 | M110: 0 | N110: 0 | O110: 0 | Q110: {=SUM(D110:O110)} -> 0
B111: TOTAL TAXES | D111: {=SUM(D107:D110)} -> 0 | E111: {=SUM(E107:E110)} -> 0 | F111: {=SUM(F107:F110)} -> 0 | G111: {=SUM(G107:G110)} -> 0 | H111: {=SUM(H107:H110)} -> 0 | I111: {=SUM(I107:I110)} -> 0 | J111: {=SUM(J107:J110)} -> 0 | K111: {=SUM(K107:K110)} -> 0 | ... O111: {=SUM(O107:O110)} -> 0 | Q111: {=SUM(Q107:Q110)} -> 0
B113: TOTAL EXPENSES | D113: {=SUM(D58,D66,D75,D96,D104)} -> 13441.7 | E113: {=SUM(E58,E66,E75,E96,E104)} -> 9888.9 | F113: {=SUM(F58,F66,F75,F96,F104)} -> 16814.8 | G113: {=SUM(G58,G66,G75,G96,G104)} -> 18128.1 | H113: {=SUM(H58,H66,H75,H96,H104)} -> 13110 | I113: {=SUM(I58,I66,I75,I96,I104)} -> 20072.6 | J113: {=SUM(J58,J66,J75,J96,J104)} -> 0 | K113: {=SUM(K58,K66,K75,K96,K104)} -> 0 | ... O113: {=SUM(O58,O66,O75,O96,O104)} -> 0 | Q113: {=SUM(Q58,Q66,Q75,Q96,Q104,Q111)} -> 91456.1

Sheet SAMPLE - Monthly Profit & Loss-
B1: MONTHLY PROFIT AND LOSS
B2: COMPANY NAME
B3: FormaCash
B5: Last Update and verification
B6: 45473
C8: TREND | D8: JANUARY | E8: FEBRUARY | F8: MARCH | G8: APRIL | H8: MAY | I8: JUNE | J8: JULY | K8: AUGUST | L8: SEPTEMBER | M8: OCTOBER | N8: NOVEMBER | O8: DECEMBER | Q8: YTD
B9: GROSS PROFIT | D9: {=D37} -> 2500 | E9: {=E37} -> 70500 | F9: {=F37} -> 46500 | G9: {=G37} -> 76500 | H9: {=H37} -> 104500 | I9: {=I37} -> 83500 | J9: {=J37} -> 96500 | K9: {=K37} -> 66000 | ... O9: {=O37} -> 0 | Q9: {=SUM(D9:O9)} -> 806000
B10: TOTAL EXPENSES | D10: {=D111} -> 166 | E10: {=E111} -> 37506 | F10: {=F111} -> 45500.98 | G10: {=G111} -> 55631.5 | H10: {=H111} -> 72766 | I10: {=I111} -> 59296 | J10: {=J111} -> 57826 | K10: {=K111} -> 42756 | ... O10: {=O111} -> 0 | Q10: {=SUM(D10:O10)} -> 547276.48
B11: PROFIT / LOSS | D11: {=D9-D10} -> 2334 | E11: {=E9-E10} -> 32994 | F11: {=F9-F10} -> 999.02 | G11: {=G9-G10} -> 20868.5 | H11: {=H9-H10} -> 31734 | I11: {=I9-I10} -> 24204 | J11: {=J9-J10} -> 38674 | K11: {=K9-K10} -> 23244 | ... O11: {=O9-O10} -> 0 | Q11: {=Q9-Q10} -> 258723.52
B13: Clients
C14: TREND | D14: JANUARY | E14: FEBRUARY | F14: MARCH | G14: APRIL | H14: MAY | I14: JUNE | J14: JULY | K14: AUGUST | L14: SEPTEMBER | M14: OCTOBER | N14: NOVEMBER | O14: DECEMBER | Q14: YTD
B15: Développement web | D15: 0 | E15: 14 | F15: 8 | G15: 12 | H15: 16 | I15: 13 | J15: 17 | K15: 13 | L15: 14 | M15: 20 | N15: 7 | Q15: {=SUM(D15:O15)} -> 134
B16: No-Code | D16: 1 | E16: 3 | F16: 6 | G16: 9 | H16: 13 | I16: 10 | J16: 8 | K16: 3 | L16: 16 | M16: 8 | N16: 6 | Q16: {=SUM(D16:O16)} -> 83
B17: TOTAUX | D17: {=SUM(D15,D16)} -> 1 | E17: {=SUM(E15,E16)} -> 17 | F17: {=SUM(F15,F16)} -> 14 | G17: {=SUM(G15,G16)} -> 21 | H17: {=SUM(H15,H16)} -> 29 | I17: {=SUM(I15,I16)} -> 23 | J17: {=SUM(J15,J16)} -> 25 | K17: {=SUM(K15,K16)} -> 16 | ... O17: {=SUM(O15,O16)} -> 0 | Q17: {=SUM(Q15,Q16)} -> 217
B19: Enter the amounts for each month below. YTD amounts, YTD tab, graph, and trend lines will populate automatically.
B20: REVENUE | C20: TREND | D20: JANUARY | E20: FEBRUARY | F20: MARCH | G20: APRIL | H20: MAY | I20: JUNE | J20: JULY | K20: AUGUST | L20: SEPTEMBER | M20: OCTOBER | N20: NOVEMBER | O20: DECEMBER | Q20: YTD
B21: Développement Web et Mobile | D21: {=SUM(4500*D15)} -> 0 | E21: {=SUM(4500*E15)} -> 63000 | F21: {=SUM(4500*F15)} -> 36000 | G21: {=SUM(4500*G15)} -> 54000 | H21: {=SUM(4500*H15)} -> 72000 | I21: {=SUM(4500*I15)} -> 58500 | J21: {=SUM(4500*J15)} -> 76500 | K21: {=SUM(4500*K15)} -> 58500 | ... O21: {=SUM(4500*O15)} -> 0 | Q21: {=SUM(D21:O21)} -> 603000
B22: No Code | D22: {=SUM(2500*D16)} -> 2500 | E22: {=SUM(2500*E16)} -> 7500 | F22: {=SUM(2500*F16)} -> 15000 | G22: {=SUM(2500*G16)} -> 22500 | H22: {=SUM(2500*H16)} -> 32500 | I22: {=SUM(2500*I16)} -> 25000 | J22: {=SUM(2500*J16)} -> 20000 | K22: {=SUM(2500*K16)} -> 7500 | ... O22: {=SUM(2500*O16)} -> 0 | Q22: {=SUM(D22:O22)} -> 207500
B23: Other Income 3 | D23: 0 | E23: 0 | F23: 0 | G23: 0 | H23: 0 | I23: 0 | J23: 0 | K23: 0 | L23: 0 | M23: 0 | N23: 0 | O23: 0 | Q23: {=SUM(D23:O23)} -> 0
B24: Other Income 4 | D24: 0 | E24: 0 | F24: 0 | G24: 0 | H24: 0 | I24: 0 | J24: 0 | K24: 0 | L24: 0 | M24: 0 | N24: 0 | O24: 0 | Q24: {=SUM(D24:O24)} -> 0
B25: Other Income 5 | D25: 0 | E25: 0 | F25: 0 | G25: 0 | H25: 0 | I25: 0 | J25: 0 | K25: 0 | L25: 0 | M25: 0 | N25: 0 | O25: 0 | Q25: {=SUM(D25:O25)} -> 0
B26: Other Income 6 | D26: 0 | E26: 0 | F26: 0 | G26: 0 | H26: 0 | I26: 0 | J26: 0 | K26: 0 | L26: 0 | M26: 0 | N26: 0 | O26: 0 | Q26: {=SUM(D26:O26)} -> 0
B27: Other Income 7 | D27: 0 | E27: 0 | F27: 0 | G27: 0 | H27: 0 | I27: 0 | J27: 0 | K27: 0 | L27: 0 | M27: 0 | N27: 0 | O27: 0 | Q27: {=SUM(D27:O27)} -> 0
B28: Other Income 8 | D28: 0 | E28: 0 | F28: 0 | G28: 0 | H28: 0 | I28: 0 | J28: 0 | K28: 0 | L28: 0 | M28: 0 | N28: 0 | O28: 0 | Q28: {=SUM(D28:O28)} -> 0
B29: TOTAL REVENUE | D29: {=SUM(D21:D28)} -> 2500 | E29: {=SUM(E21:E28)} -> 70500 | F29: {=SUM(F21:F28)} -> 51000 | G29: {=SUM(G21:G28)} -> 76500 | H29: {=SUM(H21:H28)} -> 104500 | I29: {=SUM(I21:I28)} -> 83500 | J29: {=SUM(J21:J28)} -> 96500 | K29: {=SUM(K21:K28)} -> 66000 | ... O29: {=SUM(O21:O28)} -> 0 | Q29: {=SUM(Q21:Q28)} -> 810500
B31: REDUCTIONS | C31: TREND | D31: JANUARY | E31: FEBRUARY | F31: MARCH | G31: APRIL | H31: MAY | I31: JUNE | J31: JULY | K31: AUGUST | L31: SEPTEMBER | M31: OCTOBER | N31: NOVEMBER | O31: DECEMBER | Q31: YTD
B32: Less Sales Returns | D32: 0 | E32: 0 | F32: 4500 | G32: 0 | H32: 0 | I32: 0 | J32: 0 | K32: 0 | L32: 0 | M32: 0 | N32: 0 | O32: 0 | Q32: {=SUM(D32:O32)} -> 4500
B33: Less Sales Discounts | D33: 0 | E33: 0 | F33: 0 | G33: 0 | H33: 0 | I33: 0 | J33: 0 | K33: 0 | L33: 0 | M33: 0 | N33: 0 | O33: 0 | Q33: {=SUM(D33:O33)} -> 0
B34: Less Cost of Goods Sold | D34: 0 | E34: 0 | F34: 0 | G34: 0 | H34: 0 | I34: 0 | J34: 0 | K34: 0 | L34: 0 | M34: 0 | N34: 0 | O34: 0 | Q34: {=SUM(D34:O34)} -> 0
B35: TOTAL REDUCTIONS | D35: {=SUM(D32:D34)} -> 0 | E35: {=SUM(E32:E34)} -> 0 | F35: {=SUM(F32:F34)} -> 4500 | G35: {=SUM(G32:G34)} -> 0 | H35: {=SUM(H32:H34)} -> 0 | I35: {=SUM(I32:I34)} -> 0 | J35: {=SUM(J32:J34)} -> 0 | K35: {=SUM(K32:K34)} -> 0 | ... O35: {=SUM(O32:O34)} -> 0 | Q35: {=SUM(Q32:Q34)} -> 4500
B37: GROSS PROFIT | SALES MINUS REDUCTIONS | D37: {=D29-D35} -> 2500 | E37: {=E29-E35} -> 70500 | F37: {=F29-F35} -> 46500 | G37: {=G29-G35} -> 76500 | H37: {=H29-H35} -> 104500 | I37: {=I29-I35} -> 83500 | J37: {=J29-J35} -> 96500 | K37: {=K29-K35} -> 66000 | ... O37: {=O29-O35} -> 0 | Q37: {=Q29-Q35} -> 806000
B39: EXPENSES
B40: EMPLOYEE | C40: TREND | D40: JANUARY | E40: FEBRUARY | F40: MARCH | G40: APRIL | H40: MAY | I40: JUNE | J40: JULY | K40: AUGUST | L40: SEPTEMBER | M40: OCTOBER | N40: NOVEMBER | O40: DECEMBER | Q40: YTD
B41: Josselin MORELLE | C41: Développement web | D41: 0 | E41: 0 | F41: 800 | G41: 2000 | H41: 3450 | I41: 4200 | J41: 4890 | K41: 5300 | L41: 5800 | M41: 2000 | N41: 1300 | O41: 0 | Q41: {=SUM(D41:O41)} -> 29740
B42: Zahra GUERBI | C42: Développement web | D42: 0 | E42: 0 | F42: 0 | G42: 0 | H42: 0 | I42: 0 | J42: 0 | K42: 0 | L42: 0 | M42: 0 | N42: 0 | O42: 0 | Q42: {=SUM(D42:O42)} -> 0
B43: Gaylor LOCHE | C43: Freelance | D43: 0 | E43: 4000 | F43: 4000 | G43: 0 | H43: 0 | I43: 0 | J43: 0 | K43: 0 | L43: 0 | M43: 0 | N43: 0 | O43: 0 | Q43: {=SUM(D43:O43)} -> 8000
B44: Christophe Badidou | C44: Développement web | D44: 0 | E44: 11200 | F44: 11200 | G44: 11200 | H44: 0 | I44: 0 | J44: 0 | K44: 0 | L44: 0 | M44: 0 | N44: 0 | O44: 0 | Q44: {=SUM(D44:O44)} -> 33600
B45: Emmanuel Gutman | C45: Freelance | D45: 0 | E45: 4500 | F45: 4500 | G45: 4500 | H45: 4500 | I45: 0 | J45: 0 | K45: 0 | L45: 0 | M45: 0 | N45: 0 | O45: 0 | Q45: {=SUM(D45:O45)} -> 18000
B46: Séverine Pereira | C46: Développement web | D46: 0 | E46: 0 | F46: 0 | G46: 2400 | H46: 1630 | I46: 1630 | J46: 1630 | K46: 1630 | L46: 1630 | M46: 1630 | N46: 1630 | O46: 0 | Q46: {=SUM(D46:O46)} -> 13810
B47: Tom Charmasson | C47: Développement web | D47: 0 | E47: 0 | F47: 0 | G47: 0 | H47: 2450 | I47: 2450 | J47: 2450 | K47: 2450 | L47: 2450 | M47: 2450 | N47: 2450 | O47: 0 | Q47: {=SUM(D47:O47)} -> 17150
B48: Lucas Lengrand | C48: Développement web | D48: 0 | E48: 0 | F48: 0 | G48: 0 | H48: 2200 | I48: 2200 | J48: 2200 | K48: 2200 | L48: 2200 | M48: 2200 | N48: 2200 | O48: 0 | Q48: {=SUM(D48:O48)} -> 15400
B49: Jira Zer | C49: Conseillère évolution | D49: 0 | E49: 0 | F49: 0 | G49: 0 | H49: 1300 | I49: 1300 | J49: 1300 | K49: 1300 | L49: 1300 | M49: 1300 | N49: 1300 | O49: 0 | Q49: {=SUM(D49:O49)} -> 9100
B50: Kelian Halleray | C50: Développement web | D50: 0 | E50: 0 | F50: 0 | G50: 0 | H50: 2300 | I50: 2300 | J50: 2300 | K50: 2300 | L50: 2300 | M50: 2300 | N50: 2300 | O50: 0 | Q50: {=SUM(D50:O50)} -> 16100
B51: Mathis Duperray | C51: Développement web | D51: 0 | E51: 0 | F51: 0 | G51: 0 | H51: 1420 | I51: 1420 | J51: 1420 | K51: 1420 | L51: 1420 | M51: 1420 | N51: 1420 | O51: 0 | Q51: {=SUM(D51:O51)} -> 9940
B52: Kahina Angibert | C52: No-Code | D52: 0 | E52: 0 | F52: 0 | G52: 0 | H52: 1850 | I52: 1850 | J52: 1850 | K52: 1850 | L52: 1850 | M52: 1850 | N52: 1850 | O52: 0 | Q52: {=SUM(D52:O52)} -> 12950
... B55: Mikael Tribet | C55: No-Code | D55: 0 | E55: 0 | F55: 0 | G55: 0 | H55: 1700 | I55: 1700 | J55: 1700 | K55: 1700 | L55: 1700 | M55: 1700 | N55: 1700 | O55: 0 | Q55: {=SUM(D55:O55)} -> 11900
B56: TOTAL EMPLOYEE AND LABOR EXPENSE | D56: {=SUM(D41:D55)} -> 0 | E56: {=SUM(E41:E55)} -> 19700 | F56: {=SUM(F41:F55)} -> 20500 | G56: {=SUM(G41:G55)} -> 20100 | H56: {=SUM(H41:H55)} -> 25300 | I56: {=SUM(I41:I55)} -> 21550 | J56: {=SUM(J41:J55)} -> 22240 | K56: {=SUM(K41:K55)} -> 22650 | ... O56: {=SUM(O41:O55)} -> 0 | Q56: {=SUM(Q41:Q55)} -> 213190
B58: Software | C58: TREND | D58: JANUARY | E58: FEBRUARY | F58: MARCH | G58: APRIL | H58: MAY | I58: JUNE | J58: JULY | K58: AUGUST | L58: SEPTEMBER | M58: OCTOBER | N58: NOVEMBER | O58: DECEMBER | Q58: YTD
B59: AWS | C59: 1800/users | D59: {=SUM(1800*D15)} -> 0 | E59: {=SUM(1800*E16)} -> 5400 | F59: {=SUM(1800*F16)} -> 10800 | G59: {=SUM(1800*G16)} -> 16200 | H59: {=SUM(1800*H16)} -> 23400 | I59: {=SUM(1800*I16)} -> 18000 | J59: {=SUM(1800*J16)} -> 14400 | K59: {=SUM(1800*K16)} -> 5400 | L59: {=SUM(1800*L16)} -> 28800 | ... O59: {=SUM(1800*O16)} -> 0 | Q59: {=SUM(D59:O59)} -> 147600
B60: WebStorm | C60: 600/users | D60: {=SUM(600*D15)} -> 0 | E60: {=SUM(600*E17)} -> 10200 | F60: {=SUM(600*F17)} -> 8400 | G60: {=SUM(600*G17)} -> 12600 | H60: {=SUM(600*H17)} -> 17400 | I60: {=SUM(600*I17)} -> 13800 | J60: {=SUM(600*J17)} -> 15000 | K60: {=SUM(600*K17)} -> 9600 | L60: {=SUM(600*L17)} -> 18000 | ... O60: {=SUM(600*O17)} -> 0 | Q60: {=SUM(D60:O60)} -> 129600
B61: Adobe XD | C61: 120/users | D61: {=SUM(120*D15)} -> 0 | E61: {=SUM(120*E17)} -> 2040 | F61: {=SUM(120*F17)} -> 1680 | G61: {=SUM(120*G17)} -> 2520 | H61: {=SUM(120*H17)} -> 3480 | I61: {=SUM(120*I17)} -> 2760 | J61: {=SUM(120*J17)} -> 3000 | K61: {=SUM(120*K17)} -> 1920 | L61: {=SUM(120*L17)} -> 3600 | ... O61: {=SUM(120*O17)} -> 0 | Q61: {=SUM(D61:O61)} -> 25920
B62: LMS | C62: sub constant | D62: 166 | E62: 166 | F62: 166 | G62: 166 | H62: 166 | I62: 166 | J62: 166 | K62: 166 | L62: 166 | M62: 166 | N62: 166 | O62: 0 | Q62: {=SUM(D62:O62)} -> 1826
B63: Other | D63: 0 | E63: 0 | F63: 0 | G63: 0 | H63: 0 | I63: 0 | J63: 0 | K63: 0 | L63: 0 | M63: 0 | N63: 0 | O63: 0 | Q63: {=SUM(D63:O63)} -> 0
D64: {=SUM(D59:D63)} -> 166 | E64: {=SUM(E59:E63)} -> 17806 | F64: {=SUM(F59:F63)} -> 21046 | G64: {=SUM(G59:G63)} -> 31486 | H64: {=SUM(H59:H63)} -> 44446 | I64: {=SUM(I59:I63)} -> 34726 | J64: {=SUM(J59:J63)} -> 32566 | K64: {=SUM(K59:K63)} -> 17086 | ... O64: {=SUM(O59:O63)} -> 0 | Q64: {=SUM(Q59:Q63)} -> 304946
B66: BANKING AND FINANCE | C66: TREND | D66: JANUARY | E66: FEBRUARY | F66: MARCH | G66: APRIL | H66: MAY | I66: JUNE | J66: JULY | K66: AUGUST | L66: SEPTEMBER | M66: OCTOBER | N66: NOVEMBER | O66: DECEMBER | Q66: YTD
B67: Bank Fees | D67: 0 | E67: 0 | F67: 1204.98 | G67: 1025.5 | H67: 0 | I67: 0 | J67: 0 | K67: 0 | L67: 0 | M67: 0 | N67: 0 | O67: 0 | Q67: {=SUM(D67:O67)} -> 2230.48
B68: Bad Debts | D68: 0 | E68: 0 | F68: 0 | G68: 0 | H68: 0 | I68: 0 | J68: 0 | K68: 0 | L68: 0 | M68: 0 | N68: 0 | O68: 0 | Q68: {=SUM(D68:O68)} -> 0
B69: Interest Paid | D69: 0 | E69: 0 | F69: 0 | G69: 0 | H69: 0 | I69: 0 | J69: 0 | K69: 0 | L69: 0 | M69: 0 | N69: 0 | O69: 0 | Q69: {=SUM(D69:O69)} -> 0
B70: Insurance | D70: 0 | E70: 0 | F70: 0 | G70: 0 | H70: 0 | I70: 0 | J70: 0 | K70: 0 | L70: 0 | M70: 0 | N70: 0 | O70: 0 | Q70: {=SUM(D70:O70)} -> 0
B71: Loan Fees | D71: 0 | E71: 0 | F71: 0 | G71: 0 | H71: 0 | I71: 0 | J71: 0 | K71: 0 | L71: 0 | M71: 0 | N71: 0 | O71: 0 | Q71: {=SUM(D71:O71)} -> 0
B72: Other | D72: 0 | E72: 0 | F72: 0 | G72: 0 | H72: 0 | I72: 0 | J72: 0 | K72: 0 | L72: 0 | M72: 0 | N72: 0 | O72: 0 | Q72: {=SUM(D72:O72)} -> 0
B73: TOTAL BANKING AND FINANCE | D73: {=SUM(D67:D72)} -> 0 | E73: {=SUM(E67:E72)} -> 0 | F73: {=SUM(F67:F72)} -> 1204.98 | G73: {=SUM(G67:G72)} -> 1025.5 | H73: {=SUM(H67:H72)} -> 0 | I73: {=SUM(I67:I72)} -> 0 | J73: {=SUM(J67:J72)} -> 0 | K73: {=SUM(K67:K72)} -> 0 | ... O73: {=SUM(O67:O72)} -> 0 | Q73: {=SUM(Q67:Q72)} -> 2230.48
B75: GENERAL BUSINESS | C75: TREND | D75: JANUARY | E75: FEBRUARY | F75: MARCH | G75: APRIL | H75: MAY | I75: JUNE | J75: JULY | K75: AUGUST | L75: SEPTEMBER | M75: OCTOBER | N75: NOVEMBER | O75: DECEMBER | Q75: YTD
B76: Zoom Pro | C76: 20/user | D76: 0 | E76: 0 | F76: 0 | G76: 0 | H76: 0 | I76: 0 | J76: 0 | K76: 0 | L76: 0 | M76: 0 | N76: 0 | O76: 0 | Q76: {=SUM(D76:O76)} -> 0
B77: Maintenance and Repairs - OVH Cloud | C77: sub constant | D77: 0 | E77: 0 | F77: 200 | G77: 200 | H77: 200 | I77: 200 | J77: 200 | K77: 200 | L77: 200 | M77: 200 | N77: 200 | O77: 0 | Q77: {=SUM(D77:O77)} -> 1800
B78: Telecommunication | C78: 90/user | D78: 0 | E78: 0 | F78: 180 | G78: 450 | H78: 450 | I78: 450 | J78: 450 | K78: 450 | L78: 450 | M78: 450 | N78: 450 | O78: 0 | Q78: {=SUM(D78:O78)} -> 3780
B79: Advertising, Marketing, and Promotions | C79: sub constant | D79: 0 | E79: 0 | F79: 250 | G79: 250 | H79: 250 | I79: 250 | J79: 250 | K79: 250 | L79: 250 | M79: 250 | N79: 250 | O79: 0 | Q79: {=SUM(D79:O79)} -> 2250
B80: Web Hosting | C80: sub constant | D80: 0 | E80: 0 | F80: 2000 | G80: 2000 | H80: 2000 | I80: 2000 | J80: 2000 | K80: 2000 | L80: 2000 | M80: 2000 | N80: 2000 | O80: 0 | Q80: {=SUM(D80:O80)} -> 18000
B81: LMS Manager | C81: sub constant | D81: 0 | E81: 0 | F81: 120 | G81: 120 | H81: 120 | I81: 120 | J81: 120 | K81: 120 | L81: 120 | M81: 120 | N81: 120 | O81: 0 | Q81: {=SUM(D81:O81)} -> 1080
B82: Office Supplies | D82: 0 | E82: 0 | F82: 0 | G82: 0 | H82: 0 | I82: 0 | J82: 0 | K82: 0 | L82: 0 | M82: 0 | N82: 0 | O82: 0 | Q82: {=SUM(D82:O82)} -> 0
B83: Professional Dues | D83: 0 | E83: 0 | F83: 0 | G83: 0 | H83: 0 | I83: 0 | J83: 0 | K83: 0 | L83: 0 | M83: 0 | N83: 0 | O83: 0 | Q83: {=SUM(D83:O83)} -> 0
B84: Subscriptions | D84: 0 | E84: 0 | F84: 0 | G84: 0 | H84: 0 | I84: 0 | J84: 0 | K84: 0 | L84: 0 | M84: 0 | N84: 0 | O84: 0 | Q84: {=SUM(D84:O84)} -> 0
B85: Freight | D85: 0 | E85: 0 | F85: 0 | G85: 0 | H85: 0 | I85: 0 | J85: 0 | K85: 0 | L85: 0 | M85: 0 | N85: 0 | O85: 0 | Q85: {=SUM(D85:O85)} -> 0
B86: Postage and Shipping | D86: 0 | E86: 0 | F86: 0 | G86: 0 | H86: 0 | I86: 0 | J86: 0 | K86: 0 | L86: 0 | M86: 0 | N86: 0 | O86: 0 | Q86: {=SUM(D86:O86)} -> 0
B87: Depreciation and Amortization | D87: 0 | E87: 0 | F87: 0 | G87: 0 | H87: 0 | I87: 0 | J87: 0 | K87: 0 | L87: 0 | M87: 0 | N87: 0 | O87: 0 | Q87: {=SUM(D87:O87)} -> 0
B88: Travel | D88: 0 | E88: 0 | F88: 0 | G88: 0 | H88: 0 | I88: 0 | J88: 0 | K88: 0 | L88: 0 | M88: 0 | N88: 0 | O88: 0 | Q88: {=SUM(D88:O88)} -> 0
B89: Technical Licenses | D89: 0 | E89: 0 | F89: 0 | G89: 0 | H89: 0 | I89: 0 | J89: 0 | K89: 0 | L89: 0 | M89: 0 | N89: 0 | O89: 0 | Q89: {=SUM(D89:O89)} -> 0
B90: Meals and Entertainment | D90: 0 | E90: 0 | F90: 0 | G90: 0 | H90: 0 | I90: 0 | J90: 0 | K90: 0 | L90: 0 | M90: 0 | N90: 0 | O90: 0 | Q90: {=SUM(D90:O90)} -> 0
B91: Patent Fees | D91: 0 | E91: 0 | F91: 0 | G91: 0 | H91: 0 | I91: 0 | J91: 0 | K91: 0 | L91: 0 | M91: 0 | N91: 0 | O91: 0 | Q91: {=SUM(D91:O91)} -> 0
B92: Losses from Legal Actions | D92: 0 | E92: 0 | F92: 0 | G92: 0 | H92: 0 | I92: 0 | J92: 0 | K92: 0 | L92: 0 | M92: 0 | N92: 0 | O92: 0 | Q92: {=SUM(D92:O92)} -> 0
B93: Other | D93: 0 | E93: 0 | F93: 0 | G93: 0 | H93: 0 | I93: 0 | J93: 0 | K93: 0 | L93: 0 | M93: 0 | N93: 0 | O93: 0 | Q93: {=SUM(D93:O93)} -> 0
B94: TOTAL GENERAL BUSINESS | D94: {=SUM(D76:D93)} -> 0 | E94: {=SUM(E76:E93)} -> 0 | F94: {=SUM(F76:F93)} -> 2750 | G94: {=SUM(G76:G93)} -> 3020 | H94: {=SUM(H76:H93)} -> 3020 | I94: {=SUM(I76:I93)} -> 3020 | J94: {=SUM(J76:J93)} -> 3020 | K94: {=SUM(K76:K93)} -> 3020 | ... O94: {=SUM(O76:O93)} -> 0 | Q94: {=SUM(Q76:Q93)} -> 26910
B96: VEHICLE EXPENSE | C96: TREND | D96: JANUARY | E96: FEBRUARY | F96: MARCH | G96: APRIL | H96: MAY | I96: JUNE | J96: JULY | K96: AUGUST | L96: SEPTEMBER | M96: OCTOBER | N96: NOVEMBER | O96: DECEMBER | Q96: YTD
B97: Gas | D97: 0 | E97: 0 | F97: 0 | G97: 0 | H97: 0 | I97: 0 | J97: 0 | K97: 0 | L97: 0 | M97: 0 | N97: 0 | O97: 0 | Q97: {=SUM(D97:O97)} -> 0
B98: Maintenance and Repairs | D98: 0 | E98: 0 | F98: 0 | G98: 0 | H98: 0 | I98: 0 | J98: 0 | K98: 0 | L98: 0 | M98: 0 | N98: 0 | O98: 0 | Q98: {=SUM(D98:O98)} -> 0
B99: Licensing | D99: 0 | E99: 0 | F99: 0 | G99: 0 | H99: 0 | I99: 0 | J99: 0 | K99: 0 | L99: 0 | M99: 0 | N99: 0 | O99: 0 | Q99: {=SUM(D99:O99)} -> 0
B100: Insurance | D100: 0 | E100: 0 | F100: 0 | G100: 0 | H100: 0 | I100: 0 | J100: 0 | K100: 0 | L100: 0 | M100: 0 | N100: 0 | O100: 0 | Q100: {=SUM(D100:O100)} -> 0
B101: Other | D101: 0 | E101: 0 | F101: 0 | G101: 0 | H101: 0 | I101: 0 | J101: 0 | K101: 0 | L101: 0 | M101: 0 | N101: 0 | O101: 0 | Q101: {=SUM(D101:O101)} -> 0
B102: TOTAL VEHICLE EXPENSE | D102: {=SUM(D97:D101)} -> 0 | E102: {=SUM(E97:E101)} -> 0 | F102: {=SUM(F97:F101)} -> 0 | G102: {=SUM(G97:G101)} -> 0 | H102: {=SUM(H97:H101)} -> 0 | I102: {=SUM(I97:I101)} -> 0 | J102: {=SUM(J97:J101)} -> 0 | K102: {=SUM(K97:K101)} -> 0 | ... O102: {=SUM(O97:O101)} -> 0 | Q102: {=SUM(Q97:Q101)} -> 0
B104: TAXES (not calculated) | C104: TREND | D104: JANUARY | E104: FEBRUARY | F104: MARCH | G104: APRIL | H104: MAY | I104: JUNE | J104: JULY | K104: AUGUST | L104: SEPTEMBER | M104: OCTOBER | N104: NOVEMBER | O104: DECEMBER | Q104: YTD
B105: TVA | D105: 0 | E105: 0 | F105: 30718.78 | G105: 5250 | I105: 0 | J105: 0 | K105: 0 | L105: 0 | M105: 0 | N105: 0 | O105: 0 | Q105: {=SUM(D105:O105)} -> 35968.78
B106: Disbursement fees | D106: 0 | E106: 0 | F106: 0 | G106: 0 | H106: 0 | I106: 0 | J106: 0 | K106: 0 | L106: 0 | M106: 0 | N106: 0 | O106: 0 | Q106: {=SUM(D106:O106)} -> 0
B107: Property Tax | D107: 0 | E107: 0 | F107: 0 | G107: 0 | H107: 0 | I107: 0 | J107: 0 | K107: 0 | L107: 0 | M107: 0 | N107: 0 | O107: 0 | Q107: {=SUM(D107:O107)} -> 0
B108: B&O Tax | D108: 0 | E108: 0 | F108: 0 | G108: 0 | H108: 0 | I108: 0 | J108: 0 | K108: 0 | L108: 0 | M108: 0 | N108: 0 | O108: 0 | Q108: {=SUM(D108:O108)} -> 0
B109: TOTAL TAXES | D109: {=SUM(D105:D108)} -> 0 | E109: {=SUM(E105:E108)} -> 0 | F109: {=SUM(F105:F108)} -> 30718.78 | G109: {=SUM(G105:G108)} -> 5250 | H109: {=SUM(H105:H108)} -> 0 | I109: {=SUM(I105:I108)} -> 0 | J109: {=SUM(J105:J108)} -> 0 | K109: {=SUM(K105:K108)} -> 0 | ... O109: {=SUM(O105:O108)} -> 0 | Q109: {=SUM(Q105:Q108)} -> 35968.78
B111: TOTAL EXPENSES | D111: {=SUM(D56,D64,D73,D94,D102)} -> 166 | E111: {=SUM(E56,E64,E73,E94,E102)} -> 37506 | F111: {=SUM(F56,F64,F73,F94,F102)} -> 45500.98 | G111: {=SUM(G56,G64,G73,G94,G102)} -> 55631.5 | H111: {=SUM(H56,H64,H73,H94,H102)} -> 72766 | I111: {=SUM(I56,I64,I73,I94,I102)} -> 59296 | J111: {=SUM(J56,J64,J73,J94,J102)} -> 57826 | K111: {=SUM(K56,K64,K73,K94,K102)} -> 42756 | ... O111: {=SUM(O56,O64,O73,O94,O102)} -> 0 | Q111: {=SUM(Q56,Q64,Q73,Q94,Q102,Q109)} -> 583245.26

Sheet SAMPLE - Profit & Loss YTD - Ta
B1: SAMPLE PROFIT AND LOSS YTD
B2: COMPANY NAME
B3: {='SAMPLE - Monthly Profit & Loss '!B3} -> Hackboot
B5: Last Update and verification
B6: {='SAMPLE - Monthly Profit & Loss '!B6} -> 45984
C8: YTD
B9: GROSS PROFIT | C9: {='SAMPLE - Monthly Profit & Loss '!Q9} -> 131824.98
B10: TOTAL EXPENSES | C10: {='SAMPLE - Monthly Profit & Loss '!Q10} -> 91456.1
B11: PROFIT / LOSS | C11: {='SAMPLE - Monthly Profit & Loss '!Q11} -> 40368.88
B13: REVENUE | C13: {='SAMPLE - Monthly Profit & Loss '!Q24} -> YTD
B14: {='SAMPLE - Monthly Profit & Loss '!B25} -> Pack Essentiel | C14: {='SAMPLE - Monthly Profit & Loss '!Q25} -> 5637.18
B15: {='SAMPLE - Monthly Profit & Loss '!B26} -> Pack Avantage | C15: {='SAMPLE - Monthly Profit & Loss '!Q26} -> 5215
B16: {='SAMPLE - Monthly Profit & Loss '!B27} -> Pack Élite | C16: {='SAMPLE - Monthly Profit & Loss '!Q27} -> 3720
B17: {='SAMPLE - Monthly Profit & Loss '!B28} -> VM Clash Royal | C17: {='SAMPLE - Monthly Profit & Loss '!Q28} -> 16480
B18: {='SAMPLE - Monthly Profit & Loss '!B29} -> VM Call Of Duty | C18: {='SAMPLE - Monthly Profit & Loss '!Q29} -> 72600
B19: {='SAMPLE - Monthly Profit & Loss '!B30} -> VM Overwatch 2 | C19: {='SAMPLE - Monthly Profit & Loss '!Q30} -> 28172.8
B20: {=#REF!} | C20: {=#REF!}
B21: {=#REF!} | C21: {=#REF!}
B22: TOTAL REVENUE | C22: {='SAMPLE - Monthly Profit & Loss '!Q31} -> 131824.98
B24: REDUCTIONS | C24: {='SAMPLE - Monthly Profit & Loss '!Q33} -> YTD
B25: Less sales returns | C25: {='SAMPLE - Monthly Profit & Loss '!Q34} -> 0
B26: Less sales discounts | C26: {='SAMPLE - Monthly Profit & Loss '!Q35} -> 0
B27: Less cost of goods sold | C27: {='SAMPLE - Monthly Profit & Loss '!Q36} -> 0
B28: TOTAL REDUCTIONS | C28: {='SAMPLE - Monthly Profit & Loss '!Q37} -> 0
B30: GROSS PROFIT | SALES MINUS REDUCTIONS | C30: {='SAMPLE - Monthly Profit & Loss '!Q39} -> 131824.98
B32: EXPENSES
B33: EMPLOYEE AND LABOR | C33: {='SAMPLE - Monthly Profit & Loss '!Q42} -> YTD
B34: {='SAMPLE - Monthly Profit & Loss '!B43} -> Luf | C34: {='SAMPLE - Monthly Profit & Loss '!Q43} -> 24000
B35: {='SAMPLE - Monthly Profit & Loss '!B44} -> Gengis | C35: {='SAMPLE - Monthly Profit & Loss '!Q44} -> 0
B36: {='SAMPLE - Monthly Profit & Loss '!B45} -> Other | C36: {='SAMPLE - Monthly Profit & Loss '!Q45} -> 0
B37: {='SAMPLE - Monthly Profit & Loss '!B46} -> Other | C37: {='SAMPLE - Monthly Profit & Loss '!Q46} -> 0
B38: {='SAMPLE - Monthly Profit & Loss '!B47} -> Other | C38: {='SAMPLE - Monthly Profit & Loss '!Q47} -> 0
B39: {='SAMPLE - Monthly Profit & Loss '!B48} -> Other | C39: {='SAMPLE - Monthly Profit & Loss '!Q48} -> 0
B40: {='SAMPLE - Monthly Profit & Loss '!B49} -> Other | C40: {='SAMPLE - Monthly Profit & Loss '!Q49} -> 0
B41: {='SAMPLE - Monthly Profit & Loss '!B50} -> Other | C41: {='SAMPLE - Monthly Profit & Loss '!Q50} -> 0
B42: {='SAMPLE - Monthly Profit & Loss '!B51} -> Other | C42: {='SAMPLE - Monthly Profit & Loss '!Q51} -> 0
B43: {='SAMPLE - Monthly Profit & Loss '!B52} -> Other | C43: {='SAMPLE - Monthly Profit & Loss '!Q52} -> 0
B44: {='SAMPLE - Monthly Profit & Loss '!B53} -> Other | C44: {='SAMPLE - Monthly Profit & Loss '!Q53} -> 0
B45: {='SAMPLE - Monthly Profit & Loss '!B54} -> Other | C45: {='SAMPLE - Monthly Profit & Loss '!Q54} -> 0
... B48: {='SAMPLE - Monthly Profit & Loss '!B57} -> Other | C48: {='SAMPLE - Monthly Profit & Loss '!Q57} -> 0
B49: TOTAL EMPLOYEE AND LABOR EXPENSE | C49: {='SAMPLE - Monthly Profit & Loss '!Q58} -> 24000
B51: PROFESSIONAL SERVICES | C51: {='SAMPLE - Monthly Profit & Loss '!Q60} -> YTD
B52: Outside Services | C52: {='SAMPLE - Monthly Profit & Loss '!Q61} -> 6169.7
B53: Accounting | C53: {='SAMPLE - Monthly Profit & Loss '!Q62} -> 25804.8
B54: Legal | C54: {='SAMPLE - Monthly Profit & Loss '!Q63} -> 35481.6
B55: Computing Services | C55: {='SAMPLE - Monthly Profit & Loss '!Q64} -> 0
B56: Other | C56: {='SAMPLE - Monthly Profit & Loss '!Q65} -> 0
C57: {='SAMPLE - Monthly Profit & Loss '!Q66} -> 67456.1
B59: BANKING AND FINANCE | C59: {='SAMPLE - Monthly Profit & Loss '!Q68} -> YTD
B60: Bank fees | C60: {='SAMPLE - Monthly Profit & Loss '!Q69} -> 0
B61: Bad debts | C61: {='SAMPLE - Monthly Profit & Loss '!Q70} -> 0
B62: Interest paid | C62: {='SAMPLE - Monthly Profit & Loss '!Q71} -> 0
B63: Insurance | C63: {='SAMPLE - Monthly Profit & Loss '!Q72} -> 0
B64: Loan fees | C64: {='SAMPLE - Monthly Profit & Loss '!Q73} -> 0
B65: Other | C65: {='SAMPLE - Monthly Profit & Loss '!Q74} -> 0
B66: TOTAL BANKING AND FINANCE | C66: {='SAMPLE - Monthly Profit & Loss '!Q75} -> 0
B68: GENERAL BUSINESS | C68: {='SAMPLE - Monthly Profit & Loss '!Q77} -> YTD
B69: Rent and Mortgage | C69: {='SAMPLE - Monthly Profit & Loss '!Q78} -> 0
B70: Maintenance and repairs | C70: {='SAMPLE - Monthly Profit & Loss '!Q79} -> 0
B71: Office supplies | C71: {='SAMPLE - Monthly Profit & Loss '!Q83} -> 0
B72: Utilities | C72: {='SAMPLE - Monthly Profit & Loss '!Q84} -> 0
B73: Telecommunication | C73: {='SAMPLE - Monthly Profit & Loss '!Q80} -> 0
B74: Advertising, marketing, and promotions | C74: {='SAMPLE - Monthly Profit & Loss '!Q81} -> 0
B75: Web hosting | C75: {='SAMPLE - Monthly Profit & Loss '!Q82} -> 0
B76: Professional dues | C76: {='SAMPLE - Monthly Profit & Loss '!Q85} -> 0
B77: Subscriptions | C77: {='SAMPLE - Monthly Profit & Loss '!Q86} -> 0
B78: Freight | C78: {='SAMPLE - Monthly Profit & Loss '!Q87} -> 0
B79: Postage and shipping | C79: {='SAMPLE - Monthly Profit & Loss '!Q88} -> 0
B80: Depreciation and amortization | C80: {='SAMPLE - Monthly Profit & Loss '!Q89} -> 0
B81: Travel | C81: {='SAMPLE - Monthly Profit & Loss '!Q90} -> 0
B82: Technical licenses | C82: {='SAMPLE - Monthly Profit & Loss '!Q91} -> 0
B83: Meals and entertainment | C83: {='SAMPLE - Monthly Profit & Loss '!Q92} -> 0
B84: Patent fees | C84: {='SAMPLE - Monthly Profit & Loss '!Q93} -> 0
B85: Losses from legal actions | C85: {='SAMPLE - Monthly Profit & Loss '!Q94} -> 0
B86: Other | C86: {='SAMPLE - Monthly Profit & Loss '!Q95} -> 0
B87: TOTAL GENERAL BUSINESS | C87: {='SAMPLE - Monthly Profit & Loss '!Q96} -> 0
... B97: TAXES (not calculated) | C97: {='SAMPLE - Monthly Profit & Loss '!Q106} -> YTD
B98: Disbursement fees | C98: {='SAMPLE - Monthly Profit & Loss '!Q108} -> 0
B99: Property Tax | C99: {='SAMPLE - Monthly Profit & Loss '!Q109} -> 0
B100: B&O Tax | C100: {='SAMPLE - Monthly Profit & Loss '!Q110} -> 0
B101: Other | C101: {='SAMPLE - Monthly Profit & Loss '!Q107} -> 0
B102: TOTAL TAXES | C102: {='SAMPLE - Monthly Profit & Loss '!Q111} -> 0
B104: TOTAL EXPENSES | C104: {='SAMPLE - Monthly Profit & Loss '!Q113} -> 91456.1

Sheet BLANK - Monthly Profit & Loss -
B1: MONTHLY PROFIT AND LOSS TEMPLATE
B2: COMPANY NAME
B5: TIME PERIOD REPRESENTED
C8: TREND | D8: JANUARY | E8: FEBRUARY | F8: MARCH | G8: APRIL | H8: MAY | I8: JUNE | J8: JULY | K8: AUGUST | L8: SEPTEMBER | M8: OCTOBER | N8: NOVEMBER | O8: DECEMBER | Q8: YTD
B9: GROSS PROFIT | D9: {=D31} -> 0 | E9: {=E31} -> 0 | F9: {=F31} -> 0 | G9: {=G31} -> 0 | H9: {=H31} -> 0 | I9: {=I31} -> 0 | J9: {=J31} -> 0 | K9: {=K31} -> 0 | ... O9: {=O31} -> 0 | Q9: {=SUM(D9:O9)} -> 0
B10: TOTAL EXPENSES | D10: {=D99} -> 0 | E10: {=E99} -> 0 | F10: {=F99} -> 0 | G10: {=G99} -> 0 | H10: {=H99} -> 0 | I10: {=I99} -> 0 | J10: {=J99} -> 0 | K10: {=K99} -> 0 | ... O10: {=O99} -> 0 | Q10: {=SUM(D10:O10)} -> 0
B11: PROFIT / LOSS | D11: {=D9-D10} -> 0 | E11: {=E9-E10} -> 0 | F11: {=F9-F10} -> 0 | G11: {=G9-G10} -> 0 | H11: {=H9-H10} -> 0 | I11: {=I9-I10} -> 0 | J11: {=J9-J10} -> 0 | K11: {=K9-K10} -> 0 | ... O11: {=O9-O10} -> 0 | Q11: {=Q9-Q10} -> 0
B13: Enter the amounts for each month below. YTD amounts, YTD tab, graph, and trend lines will populate automatically.
B14: REVENUE | C14: TREND | D14: JANUARY | E14: FEBRUARY | F14: MARCH | G14: APRIL | H14: MAY | I14: JUNE | J14: JULY | K14: AUGUST | L14: SEPTEMBER | M14: OCTOBER | N14: NOVEMBER | O14: DECEMBER | Q14: YTD
B15: Income from Sales | D15: 0 | E15: 0 | F15: 0 | G15: 0 | H15: 0 | I15: 0 | J15: 0 | K15: 0 | L15: 0 | M15: 0 | N15: 0 | O15: 0 | Q15: {=SUM(D15:O15)} -> 0
B16: Adjustments to Earnings | D16: 0 | E16: 0 | F16: 0 | G16: 0 | H16: 0 | I16: 0 | J16: 0 | K16: 0 | L16: 0 | M16: 0 | N16: 0 | O16: 0 | Q16: {=SUM(D16:O16)} -> 0
B17: Sales of Assets | D17: 0 | E17: 0 | F17: 0 | G17: 0 | H17: 0 | I17: 0 | J17: 0 | K17: 0 | L17: 0 | M17: 0 | N17: 0 | O17: 0 | Q17: {=SUM(D17:O17)} -> 0
B18: Gains from Legal Actions | D18: 0 | E18: 0 | F18: 0 | G18: 0 | H18: 0 | I18: 0 | J18: 0 | K18: 0 | L18: 0 | M18: 0 | N18: 0 | O18: 0 | Q18: {=SUM(D18:O18)} -> 0
B19: Interest Received | D19: 0 | E19: 0 | F19: 0 | G19: 0 | H19: 0 | I19: 0 | J19: 0 | K19: 0 | L19: 0 | M19: 0 | N19: 0 | O19: 0 | Q19: {=SUM(D19:O19)} -> 0
B20: Other Income 1 | D20: 0 | E20: 0 | F20: 0 | G20: 0 | H20: 0 | I20: 0 | J20: 0 | K20: 0 | L20: 0 | M20: 0 | N20: 0 | O20: 0 | Q20: {=SUM(D20:O20)} -> 0
B21: Other Income 2 | D21: 0 | E21: 0 | F21: 0 | G21: 0 | H21: 0 | I21: 0 | J21: 0 | K21: 0 | L21: 0 | M21: 0 | N21: 0 | O21: 0 | Q21: {=SUM(D21:O21)} -> 0
B22: Other Income 3 | D22: 0 | E22: 0 | F22: 0 | G22: 0 | H22: 0 | I22: 0 | J22: 0 | K22: 0 | L22: 0 | M22: 0 | N22: 0 | O22: 0 | Q22: {=SUM(D22:O22)} -> 0
B23: TOTAL REVENUE | D23: {=SUM(D15:D22)} -> 0 | E23: {=SUM(E15:E22)} -> 0 | F23: {=SUM(F15:F22)} -> 0 | G23: {=SUM(G15:G22)} -> 0 | H23: {=SUM(H15:H22)} -> 0 | I23: {=SUM(I15:I22)} -> 0 | J23: {=SUM(J15:J22)} -> 0 | K23: {=SUM(K15:K22)} -> 0 | ... O23: {=SUM(O15:O22)} -> 0 | Q23: {=SUM(Q15:Q22)} -> 0
B25: REDUCTIONS | C25: TREND | D25: JANUARY | E25: FEBRUARY | F25: MARCH | G25: APRIL | H25: MAY | I25: JUNE | J25: JULY | K25: AUGUST | L25: SEPTEMBER | M25: OCTOBER | N25: NOVEMBER | O25: DECEMBER | Q25: YTD
B26: Less Sales Returns | D26: 0 | E26: 0 | F26: 0 | G26: 0 | H26: 0 | I26: 0 | J26: 0 | K26: 0 | L26: 0 | M26: 0 | N26: 0 | O26: 0 | Q26: {=SUM(D26:O26)} -> 0
B27: Less Sales Discounts | D27: 0 | E27: 0 | F27: 0 | G27: 0 | H27: 0 | I27: 0 | J27: 0 | K27: 0 | L27: 0 | M27: 0 | N27: 0 | O27: 0 | Q27: {=SUM(D27:O27)} -> 0
B28: Less Cost of Goods Sold | D28: 0 | E28: 0 | F28: 0 | G28: 0 | H28: 0 | I28: 0 | J28: 0 | K28: 0 | L28: 0 | M28: 0 | N28: 0 | O28: 0 | Q28: {=SUM(D28:O28)} -> 0
B29: TOTAL REDUCTIONS | D29: {=SUM(D26:D28)} -> 0 | E29: {=SUM(E26:E28)} -> 0 | F29: {=SUM(F26:F28)} -> 0 | G29: {=SUM(G26:G28)} -> 0 | H29: {=SUM(H26:H28)} -> 0 | I29: {=SUM(I26:I28)} -> 0 | J29: {=SUM(J26:J28)} -> 0 | K29: {=SUM(K26:K28)} -> 0 | ... O29: {=SUM(O26:O28)} -> 0 | Q29: {=SUM(Q26:Q28)} -> 0
B31: GROSS PROFIT | SALES MINUS REDUCTIONS | D31: {=D23-D29} -> 0 | E31: {=E23-E29} -> 0 | F31: {=F23-F29} -> 0 | G31: {=G23-G29} -> 0 | H31: {=H23-H29} -> 0 | I31: {=I23-I29} -> 0 | J31: {=J23-J29} -> 0 | K31: {=K23-K29} -> 0 | ... O31: {=O23-O29} -> 0 | Q31: {=Q23-Q29} -> 0
B33: EXPENSES
B34: EMPLOYEE AND LABOR | C34: TREND | D34: JANUARY | E34: FEBRUARY | F34: MARCH | G34: APRIL | H34: MAY | I34: JUNE | J34: JULY | K34: AUGUST | L34: SEPTEMBER | M34: OCTOBER | N34: NOVEMBER | O34: DECEMBER | Q34: YTD
B35: Salaries | D35: 0 | E35: 0 | F35: 0 | G35: 0 | H35: 0 | I35: 0 | J35: 0 | K35: 0 | L35: 0 | M35: 0 | N35: 0 | O35: 0 | Q35: {=SUM(D35:O35)} -> 0
B36: Wages | D36: 0 | E36: 0 | F36: 0 | G36: 0 | H36: 0 | I36: 0 | J36: 0 | K36: 0 | L36: 0 | M36: 0 | N36: 0 | O36: 0 | Q36: {=SUM(D36:O36)} -> 0
B37: Benefits | D37: 0 | E37: 0 | F37: 0 | G37: 0 | H37: 0 | I37: 0 | J37: 0 | K37: 0 | L37: 0 | M37: 0 | N37: 0 | O37: 0 | Q37: {=SUM(D37:O37)} -> 0
B38: Pension/Retirement | D38: 0 | E38: 0 | F38: 0 | G38: 0 | H38: 0 | I38: 0 | J38: 0 | K38: 0 | L38: 0 | M38: 0 | N38: 0 | O38: 0 | Q38: {=SUM(D38:O38)} -> 0
B39: Commissions | D39: 0 | E39: 0 | F39: 0 | G39: 0 | H39: 0 | I39: 0 | J39: 0 | K39: 0 | L39: 0 | M39: 0 | N39: 0 | O39: 0 | Q39: {=SUM(D39:O39)} -> 0
B40: Workers Comp | D40: 0 | E40: 0 | F40: 0 | G40: 0 | H40: 0 | I40: 0 | J40: 0 | K40: 0 | L40: 0 | M40: 0 | N40: 0 | O40: 0 | Q40: {=SUM(D40:O40)} -> 0
B41: Contract Labor | D41: 0 | E41: 0 | F41: 0 | G41: 0 | H41: 0 | I41: 0 | J41: 0 | K41: 0 | L41: 0 | M41: 0 | N41: 0 | O41: 0 | Q41: {=SUM(D41:O41)} -> 0
B42: Training | D42: 0 | E42: 0 | F42: 0 | G42: 0 | H42: 0 | I42: 0 | J42: 0 | K42: 0 | L42: 0 | M42: 0 | N42: 0 | O42: 0 | Q42: {=SUM(D42:O42)} -> 0
B43: Other | D43: 0 | E43: 0 | F43: 0 | G43: 0 | H43: 0 | I43: 0 | J43: 0 | K43: 0 | L43: 0 | M43: 0 | N43: 0 | O43: 0 | Q43: {=SUM(D43:O43)} -> 0
B44: TOTAL EMPLOYEE AND LABOR EXPENSE | D44: {=SUM(D35:D43)} -> 0 | E44: {=SUM(E35:E43)} -> 0 | F44: {=SUM(F35:F43)} -> 0 | G44: {=SUM(G35:G43)} -> 0 | H44: {=SUM(H35:H43)} -> 0 | I44: {=SUM(I35:I43)} -> 0 | J44: {=SUM(J35:J43)} -> 0 | K44: {=SUM(K35:K43)} -> 0 | ... O44: {=SUM(O35:O43)} -> 0 | Q44: {=SUM(Q35:Q43)} -> 0
B46: PROFESSIONAL SERVICES | C46: TREND | D46: JANUARY | E46: FEBRUARY | F46: MARCH | G46: APRIL | H46: MAY | I46: JUNE | J46: JULY | K46: AUGUST | L46: SEPTEMBER | M46: OCTOBER | N46: NOVEMBER | O46: DECEMBER | Q46: YTD
B47: Outside Services | D47: 0 | E47: 0 | F47: 0 | G47: 0 | H47: 0 | I47: 0 | J47: 0 | K47: 0 | L47: 0 | M47: 0 | N47: 0 | O47: 0 | Q47: {=SUM(D47:O47)} -> 0
B48: Accounting | D48: 0 | E48: 0 | F48: 0 | G48: 0 | H48: 0 | I48: 0 | J48: 0 | K48: 0 | L48: 0 | M48: 0 | N48: 0 | O48: 0 | Q48: {=SUM(D48:O48)} -> 0
B49: Legal | D49: 0 | E49: 0 | F49: 0 | G49: 0 | H49: 0 | I49: 0 | J49: 0 | K49: 0 | L49: 0 | M49: 0 | N49: 0 | O49: 0 | Q49: {=SUM(D49:O49)} -> 0
B50: Other | D50: 0 | E50: 0 | F50: 0 | G50: 0 | H50: 0 | I50: 0 | J50: 0 | K50: 0 | L50: 0 | M50: 0 | N50: 0 | O50: 0 | Q50: {=SUM(D50:O50)} -> 0
B51: Other | D51: 0 | E51: 0 | F51: 0 | G51: 0 | H51: 0 | I51: 0 | J51: 0 | K51: 0 | L51: 0 | M51: 0 | N51: 0 | O51: 0 | Q51: {=SUM(D51:O51)} -> 0
D52: {=SUM(D47:D51)} -> 0 | E52: {=SUM(E47:E51)} -> 0 | F52: {=SUM(F47:F51)} -> 0 | G52: {=SUM(G47:G51)} -> 0 | H52: {=SUM(H47:H51)} -> 0 | I52: {=SUM(I47:I51)} -> 0 | J52: {=SUM(J47:J51)} -> 0 | K52: {=SUM(K47:K51)} -> 0 | ... O52: {=SUM(O47:O51)} -> 0 | Q52: {=SUM(Q47:Q51)} -> 0
B54: BANKING AND FINANCE | C54: TREND | D54: JANUARY | E54: FEBRUARY | F54: MARCH | G54: APRIL | H54: MAY | I54: JUNE | J54: JULY | K54: AUGUST | L54: SEPTEMBER | M54: OCTOBER | N54: NOVEMBER | O54: DECEMBER | Q54: YTD
B55: Bank Fees | D55: 0 | E55: 0 | F55: 0 | G55: 0 | H55: 0 | I55: 0 | J55: 0 | K55: 0 | L55: 0 | M55: 0 | N55: 0 | O55: 0 | Q55: {=SUM(D55:O55)} -> 0
B56: Bad Debts | D56: 0 | E56: 0 | F56: 0 | G56: 0 | H56: 0 | I56: 0 | J56: 0 | K56: 0 | L56: 0 | M56: 0 | N56: 0 | O56: 0 | Q56: {=SUM(D56:O56)} -> 0
B57: Interest Paid | D57: 0 | E57: 0 | F57: 0 | G57: 0 | H57: 0 | I57: 0 | J57: 0 | K57: 0 | L57: 0 | M57: 0 | N57: 0 | O57: 0 | Q57: {=SUM(D57:O57)} -> 0
B58: Insurance | D58: 0 | E58: 0 | F58: 0 | G58: 0 | H58: 0 | I58: 0 | J58: 0 | K58: 0 | L58: 0 | M58: 0 | N58: 0 | O58: 0 | Q58: {=SUM(D58:O58)} -> 0
B59: Loan Fees | D59: 0 | E59: 0 | F59: 0 | G59: 0 | H59: 0 | I59: 0 | J59: 0 | K59: 0 | L59: 0 | M59: 0 | N59: 0 | O59: 0 | Q59: {=SUM(D59:O59)} -> 0
B60: Other | D60: 0 | E60: 0 | F60: 0 | G60: 0 | H60: 0 | I60: 0 | J60: 0 | K60: 0 | L60: 0 | M60: 0 | N60: 0 | O60: 0 | Q60: {=SUM(D60:O60)} -> 0
B61: TOTAL BANKING AND FINANCE | D61: {=SUM(D55:D60)} -> 0 | E61: {=SUM(E55:E60)} -> 0 | F61: {=SUM(F55:F60)} -> 0 | G61: {=SUM(G55:G60)} -> 0 | H61: {=SUM(H55:H60)} -> 0 | I61: {=SUM(I55:I60)} -> 0 | J61: {=SUM(J55:J60)} -> 0 | K61: {=SUM(K55:K60)} -> 0 | ... O61: {=SUM(O55:O60)} -> 0 | Q61: {=SUM(Q55:Q60)} -> 0
B63: GENERAL BUSINESS | C63: TREND | D63: JANUARY | E63: FEBRUARY | F63: MARCH | G63: APRIL | H63: MAY | I63: JUNE | J63: JULY | K63: AUGUST | L63: SEPTEMBER | M63: OCTOBER | N63: NOVEMBER | O63: DECEMBER | Q63: YTD
B64: Rent and Mortgage | D64: 0 | E64: 0 | F64: 0 | G64: 0 | H64: 0 | I64: 0 | J64: 0 | K64: 0 | L64: 0 | M64: 0 | N64: 0 | O64: 0 | Q64: {=SUM(D64:O64)} -> 0
B65: Maintenance and Repairs | D65: 0 | E65: 0 | F65: 0 | G65: 0 | H65: 0 | I65: 0 | J65: 0 | K65: 0 | L65: 0 | M65: 0 | N65: 0 | O65: 0 | Q65: {=SUM(D65:O65)} -> 0
B66: Office Supplies | D66: 0 | E66: 0 | F66: 0 | G66: 0 | H66: 0 | I66: 0 | J66: 0 | K66: 0 | L66: 0 | M66: 0 | N66: 0 | O66: 0 | Q66: {=SUM(D66:O66)} -> 0
B67: Utilities | D67: 0 | E67: 0 | F67: 0 | G67: 0 | H67: 0 | I67: 0 | J67: 0 | K67: 0 | L67: 0 | M67: 0 | N67: 0 | O67: 0 | Q67: {=SUM(D67:O67)} -> 0
B68: Telecommunication | D68: 0 | E68: 0 | F68: 0 | G68: 0 | H68: 0 | I68: 0 | J68: 0 | K68: 0 | L68: 0 | M68: 0 | N68: 0 | O68: 0 | Q68: {=SUM(D68:O68)} -> 0
B69: Advertising, Marketing, and Promotions | D69: 0 | E69: 0 | F69: 0 | G69: 0 | H69: 0 | I69: 0 | J69: 0 | K69: 0 | L69: 0 | M69: 0 | N69: 0 | O69: 0 | Q69: {=SUM(D69:O69)} -> 0
B70: Web Hosting | D70: 0 | E70: 0 | F70: 0 | G70: 0 | H70: 0 | I70: 0 | J70: 0 | K70: 0 | L70: 0 | M70: 0 | N70: 0 | O70: 0 | Q70: {=SUM(D70:O70)} -> 0
B71: Professional Dues | D71: 0 | E71: 0 | F71: 0 | G71: 0 | H71: 0 | I71: 0 | J71: 0 | K71: 0 | L71: 0 | M71: 0 | N71: 0 | O71: 0 | Q71: {=SUM(D71:O71)} -> 0
B72: Subscriptions | D72: 0 | E72: 0 | F72: 0 | G72: 0 | H72: 0 | I72: 0 | J72: 0 | K72: 0 | L72: 0 | M72: 0 | N72: 0 | O72: 0 | Q72: {=SUM(D72:O72)} -> 0
B73: Freight | D73: 0 | E73: 0 | F73: 0 | G73: 0 | H73: 0 | I73: 0 | J73: 0 | K73: 0 | L73: 0 | M73: 0 | N73: 0 | O73: 0 | Q73: {=SUM(D73:O73)} -> 0
B74: Postage and Shipping | D74: 0 | E74: 0 | F74: 0 | G74: 0 | H74: 0 | I74: 0 | J74: 0 | K74: 0 | L74: 0 | M74: 0 | N74: 0 | O74: 0 | Q74: {=SUM(D74:O74)} -> 0
B75: Depreciation and Amortization | D75: 0 | E75: 0 | F75: 0 | G75: 0 | H75: 0 | I75: 0 | J75: 0 | K75: 0 | L75: 0 | M75: 0 | N75: 0 | O75: 0 | Q75: {=SUM(D75:O75)} -> 0
... B81: Other | D81: 0 | E81: 0 | F81: 0 | G81: 0 | H81: 0 | I81: 0 | J81: 0 | K81: 0 | L81: 0 | M81: 0 | N81: 0 | O81: 0 | Q81: {=SUM(D81:O81)} -> 0
B82: TOTAL GENERAL BUSINESS | D82: {=SUM(D64:D81)} -> 0 | E82: {=SUM(E64:E81)} -> 0 | F82: {=SUM(F64:F81)} -> 0 | G82: {=SUM(G64:G81)} -> 0 | H82: {=SUM(H64:H81)} -> 0 | I82: {=SUM(I64:I81)} -> 0 | J82: {=SUM(J64:J81)} -> 0 | K82: {=SUM(K64:K81)} -> 0 | ... O82: {=SUM(O64:O81)} -> 0 | Q82: {=SUM(Q64:Q81)} -> 0
B84: VEHICLE EXPENSE | C84: TREND | D84: JANUARY | E84: FEBRUARY | F84: MARCH | G84: APRIL | H84: MAY | I84: JUNE | J84: JULY | K84: AUGUST | L84: SEPTEMBER | M84: OCTOBER | N84: NOVEMBER | O84: DECEMBER | Q84: YTD
B85: Gas | D85: 0 | E85: 0 | F85: 0 | G85: 0 | H85: 0 | I85: 0 | J85: 0 | K85: 0 | L85: 0 | M85: 0 | N85: 0 | O85: 0 | Q85: {=SUM(D85:O85)} -> 0
B86: Maintenance and Repairs | D86: 0 | E86: 0 | F86: 0 | G86: 0 | H86: 0 | I86: 0 | J86: 0 | K86: 0 | L86: 0 | M86: 0 | N86: 0 | O86: 0 | Q86: {=SUM(D86:O86)} -> 0
B87: Licensing | D87: 0 | E87: 0 | F87: 0 | G87: 0 | H87: 0 | I87: 0 | J87: 0 | K87: 0 | L87: 0 | M87: 0 | N87: 0 | O87: 0 | Q87: {=SUM(D87:O87)} -> 0
B88: Insurance | D88: 0 | E88: 0 | F88: 0 | G88: 0 | H88: 0 | I88: 0 | J88: 0 | K88: 0 | L88: 0 | M88: 0 | N88: 0 | O88: 0 | Q88: {=SUM(D88:O88)} -> 0
B89: Other | D89: 0 | E89: 0 | F89: 0 | G89: 0 | H89: 0 | I89: 0 | J89: 0 | K89: 0 | L89: 0 | M89: 0 | N89: 0 | O89: 0 | Q89: {=SUM(D89:O89)} -> 0
B90: TOTAL VEHICLE EXPENSE | D90: {=SUM(D85:D89)} -> 0 | E90: {=SUM(E85:E89)} -> 0 | F90: {=SUM(F85:F89)} -> 0 | G90: {=SUM(G85:G89)} -> 0 | H90: {=SUM(H85:H89)} -> 0 | I90: {=SUM(I85:I89)} -> 0 | J90: {=SUM(J85:J89)} -> 0 | K90: {=SUM(K85:K89)} -> 0 | ... O90: {=SUM(O85:O89)} -> 0 | Q90: {=SUM(Q85:Q89)} -> 0
B92: TAXES | C92: TREND | D92: JANUARY | E92: FEBRUARY | F92: MARCH | G92: APRIL | H92: MAY | I92: JUNE | J92: JULY | K92: AUGUST | L92: SEPTEMBER | M92: OCTOBER | N92: NOVEMBER | O92: DECEMBER | Q92: YTD
B93: Sales Tax | D93: 0 | E93: 0 | F93: 0 | G93: 0 | H93: 0 | I93: 0 | J93: 0 | K93: 0 | L93: 0 | M93: 0 | N93: 0 | O93: 0 | Q93: {=SUM(D93:O93)} -> 0
B94: Property Tax | D94: 0 | E94: 0 | F94: 0 | G94: 0 | H94: 0 | I94: 0 | J94: 0 | K94: 0 | L94: 0 | M94: 0 | N94: 0 | O94: 0 | Q94: {=SUM(D94:O94)} -> 0
B95: B&O Tax | D95: 0 | E95: 0 | F95: 0 | G95: 0 | H95: 0 | I95: 0 | J95: 0 | K95: 0 | L95: 0 | M95: 0 | N95: 0 | O95: 0 | Q95: {=SUM(D95:O95)} -> 0
B96: Other | D96: 0 | E96: 0 | F96: 0 | G96: 0 | H96: 0 | I96: 0 | J96: 0 | K96: 0 | L96: 0 | M96: 0 | N96: 0 | O96: 0 | Q96: {=SUM(D96:O96)} -> 0
B97: TOTAL TAXES | D97: {=SUM(D93:D96)} -> 0 | E97: {=SUM(E93:E96)} -> 0 | F97: {=SUM(F93:F96)} -> 0 | G97: {=SUM(G93:G96)} -> 0 | H97: {=SUM(H93:H96)} -> 0 | I97: {=SUM(I93:I96)} -> 0 | J97: {=SUM(J93:J96)} -> 0 | K97: {=SUM(K93:K96)} -> 0 | ... O97: {=SUM(O93:O96)} -> 0 | Q97: {=SUM(Q93:Q96)} -> 0
B99: TOTAL EXPENSES | D99: {=SUM(D44,D52,D61,D82,D90,D97)} -> 0 | E99: {=SUM(E44,E52,E61,E82,E90,E97)} -> 0 | F99: {=SUM(F44,F52,F61,F82,F90,F97)} -> 0 | G99: {=SUM(G44,G52,G61,G82,G90,G97)} -> 0 | H99: {=SUM(H44,H52,H61,H82,H90,H97)} -> 0 | I99: {=SUM(I44,I52,I61,I82,I90,I97)} -> 0 | J99: {=SUM(J44,J52,J61,J82,J90,J97)} -> 0 | K99: {=SUM(K44,K52,K61,K82,K90,K97)} -> 0 | ... O99: {=SUM(O44,O52,O61,O82,O90,O97)} -> 0 | Q99: {=SUM(Q44,Q52,Q61,Q82,Q90,Q97)} -> 0

Sheet BLANK - Profit & Loss YTD - Tab
B1: SAMPLE PROFIT AND LOSS YTD | E1: Data on this tab will populate automatically.
B2: COMPANY NAME
B3: {='BLANK - Monthly Profit & Loss -'!B3} -> 0
B5: TIME PERIOD REPRESENTED
B6: {='BLANK - Monthly Profit & Loss -'!B6} -> 0
C8: YTD
B9: GROSS PROFIT | C9: {='BLANK - Monthly Profit & Loss -'!Q9} -> 0
B10: TOTAL EXPENSES | C10: {='BLANK - Monthly Profit & Loss -'!Q10} -> 0
B11: PROFIT / LOSS | C11: {='BLANK - Monthly Profit & Loss -'!Q11} -> 0
B13: REVENUE | C13: {='BLANK - Monthly Profit & Loss -'!Q14} -> YTD
B14: Income from sales | C14: {='BLANK - Monthly Profit & Loss -'!Q15} -> 0
B15: Adjustments to earnings | C15: {='BLANK - Monthly Profit & Loss -'!Q16} -> 0
B16: Sales of assets | C16: {='BLANK - Monthly Profit & Loss -'!Q17} -> 0
B17: Gains from legal actions | C17: {='BLANK - Monthly Profit & Loss -'!Q18} -> 0
B18: Interest received | C18: {='BLANK - Monthly Profit & Loss -'!Q19} -> 0
B19: Other income 1 | C19: {='BLANK - Monthly Profit & Loss -'!Q20} -> 0
B20: Other income 2 | C20: {='BLANK - Monthly Profit & Loss -'!Q21} -> 0
B21: Other income 3 | C21: {='BLANK - Monthly Profit & Loss -'!Q22} -> 0
B22: TOTAL REVENUE | C22: {='BLANK - Monthly Profit & Loss -'!Q23} -> 0
B24: REDUCTIONS | C24: {='BLANK - Monthly Profit & Loss -'!Q25} -> YTD
B25: Less sales returns | C25: {='BLANK - Monthly Profit & Loss -'!Q26} -> 0
... B30: GROSS PROFIT | SALES MINUS REDUCTIONS | C30: {='BLANK - Monthly Profit & Loss -'!Q31} -> 0
B32: EXPENSES
B33: EMPLOYEE AND LABOR | C33: {='BLANK - Monthly Profit & Loss -'!Q34} -> YTD
B34: Salaries | C34: {='BLANK - Monthly Profit & Loss -'!Q35} -> 0
B35: Wages | C35: {='BLANK - Monthly Profit & Loss -'!Q36} -> 0
B36: Benefits | C36: {='BLANK - Monthly Profit & Loss -'!Q37} -> 0
B37: Pension/retirement | C37: {='BLANK - Monthly Profit & Loss -'!Q38} -> 0
B38: Commissions | C38: {='BLANK - Monthly Profit & Loss -'!Q39} -> 0
B39: Workers comp | C39: {='BLANK - Monthly Profit & Loss -'!Q40} -> 0
B40: Contract labor | C40: {='BLANK - Monthly Profit & Loss -'!Q41} -> 0
B41: Training | C41: {='BLANK - Monthly Profit & Loss -'!Q42} -> 0
B42: Other | C42: {='BLANK - Monthly Profit & Loss -'!Q43} -> 0
B43: TOTAL EMPLOYEE AND LABOR EXPENSE | C43: {='BLANK - Monthly Profit & Loss -'!Q44} -> 0
B45: PROFESSIONAL SERVICES | C45: {='BLANK - Monthly Profit & Loss -'!Q46} -> YTD
... B50: Other | C50: {='BLANK - Monthly Profit & Loss -'!Q51} -> 0
C51: {='BLANK - Monthly Profit & Loss -'!Q52} -> 0
B53: BANKING AND FINANCE | C53: {='BLANK - Monthly Profit & Loss -'!Q54} -> YTD
B54: Bank fees | C54: {='BLANK - Monthly Profit & Loss -'!Q55} -> 0
B55: Bad debts | C55: {='BLANK - Monthly Profit & Loss -'!Q56} -> 0
B56: Interest paid | C56: {='BLANK - Monthly Profit & Loss -'!Q57} -> 0
B57: Insurance | C57: {='BLANK - Monthly Profit & Loss -'!Q58} -> 0
B58: Loan fees | C58: {='BLANK - Monthly Profit & Loss -'!Q59} -> 0
B59: Other | C59: {='BLANK - Monthly Profit & Loss -'!Q60} -> 0
B60: TOTAL BANKING AND FINANCE | C60: {='BLANK - Monthly Profit & Loss -'!Q61} -> 0
B62: GENERAL BUSINESS | C62: {='BLANK - Monthly Profit & Loss -'!Q63} -> YTD
B63: Rent and Mortgage | C63: {='BLANK - Monthly Profit & Loss -'!Q64} -> 0
B64: Maintenance and repairs | C64: {='BLANK - Monthly Profit & Loss -'!Q65} -> 0
B65: Office supplies | C65: {='BLANK - Monthly Profit & Loss -'!Q66} -> 0
... B98: TOTAL EXPENSES | C98: {='BLANK - Monthly Profit & Loss -'!Q99} -> 0
